{
  "resourceType": "Bundle",
  "entry": [
    {
      "fullUrl": "urn:uuid:daee98c5-4e67-45c0-acb2-9e134f61cdb2",
      "resource": {
        "resourceType": "MessageHeader",
        "destination": [
          {
            "endpoint": "https//fhir.mft.nhs.uk/Endpoint/LIMS",
            "receiver": {
              "identifier": {
                "system": "https://fhir.nhs.uk/Id/ods-organization-code",
                "value": "699X0"
              }
            }
          }
        ],
        "eventCoding": {
          "code": "O21",
          "system": "http://terminology.hl7.org/CodeSystem/v2-0003"
        },
        "focus": [
          {
            "reference": "urn:uuid:40e1b2cf-8e51-4478-b929-3c06be2e3a4e"
          }
        ],
        "sender": {
          "identifier": {
            "system": "https://fhir.nhs.uk/Id/ods-organization-code",
            "value": "REP"
          }
        },
        "source": {
          "endpoint": "https://fhir.nwgenomics.nhs.uk/Endpoint/EXPANSE_EPR",
          "software": "NW GLH"
        }
      }
    },
    {
      "fullUrl": "urn:uuid:3dda2513-de5d-47fd-a734-bc31c6a623d6",
      "resource": {
        "resourceType": "Patient",
        "address": [
          {
            "city": "Liverpool",
            "line": [
              "15 Town Road"
            ],
            "postalCode": "L1 0AJ"
          }
        ],
        "birthDate": "1996-04-15",
        "gender": "female",
        "identifier": [
          {
            "assigner": {
              "identifier": {
                "system": "https://fhir.nhs.uk/Id/ods-organization-code",
                "value": "REP"
              }
            },
            "system": "https://liverpoolwomens.nhs.uk/Id/medical-record-number",
            "type": {
              "coding": [
                {
                  "code": "MR",
                  "system": "http://terminology.hl7.org/CodeSystem/v2-0203"
                }
              ]
            },
            "value": "W0007125"
          }
        ],
        "name": [
          {
            "family": "test",
            "given": [
              "biochemistry"
            ]
          }
        ]
      }
    },
    {
      "fullUrl": "urn:uuid:47f4c2b8-f2b5-4e2b-a9b0-e3aecd6d33c3",
      "resource": {
        "resourceType": "Encounter",
        "class": {
          "code": "OBSENC",
          "system": "http://terminology.hl7.org/CodeSystem/v3-ActCode"
        },
        "identifier": [
          {
            "assigner": {
              "identifier": {
                "system": "https://fhir.nhs.uk/Id/ods-organization-code",
                "value": "REP"
              }
            },
            "type": {
              "coding": [
                {
                  "code": "VN",
                  "system": "http://terminology.hl7.org/CodeSystem/v2-0203"
                }
              ]
            },
            "value": "L00000073528"
          }
        ],
        "status": "finished",
        "subject": {
          "reference": "urn:uuid:3dda2513-de5d-47fd-a734-bc31c6a623d6"
        }
      }
    },
    {
      "fullUrl": "urn:uuid:a06eccb2-7b6c-46a9-a1a2-8ecf863d6b54",
      "resource": {
        "resourceType": "Observation",
        "category": [
          {
            "coding": [
              {
                "code": "laboratory",
                "system": "http://terminology.hl7.org/CodeSystem/observation-category"
              }
            ]
          },
          {
            "coding": [
              {
                "code": "GE",
                "system": "http://terminology.hl7.org/CodeSystem/v2-0074"
              }
            ]
          }
        ],
        "code": {
          "coding": [
            {
              "code": "Referring-Clinician-Telephone:",
              "display": "01512277372"
            }
          ]
        },
        "performer": [
          {
            "identifier": {
              "system": "https://fhir.nhs.uk/Id/ods-organization-code",
              "value": "699X0"
            },
            "type": "Organization"
          }
        ],
        "status": "final",
        "subject": {
          "reference": "urn:uuid:3dda2513-de5d-47fd-a734-bc31c6a623d6"
        }
      }
    },
    {
      "fullUrl": "urn:uuid:66f2cdb5-4422-487b-9b18-8f305ceab5f5",
      "resource": {
        "resourceType": "Observation",
        "category": [
          {
            "coding": [
              {
                "code": "laboratory",
                "system": "http://terminology.hl7.org/CodeSystem/observation-category"
              }
            ]
          },
          {
            "coding": [
              {
                "code": "GE",
                "system": "http://terminology.hl7.org/CodeSystem/v2-0074"
              }
            ]
          }
        ],
        "code": {
          "coding": [
            {
              "code": "Age-at-collection:",
              "display": "123"
            }
          ]
        },
        "performer": [
          {
            "identifier": {
              "system": "https://fhir.nhs.uk/Id/ods-organization-code",
              "value": "699X0"
            },
            "type": "Organization"
          }
        ],
        "status": "final",
        "subject": {
          "reference": "urn:uuid:3dda2513-de5d-47fd-a734-bc31c6a623d6"
        }
      }
    },
    {
      "fullUrl": "urn:uuid:5d85f321-ebe7-48b8-ac6c-6b9299023cf2",
      "resource": {
        "resourceType": "Observation",
        "category": [
          {
            "coding": [
              {
                "code": "laboratory",
                "system": "http://terminology.hl7.org/CodeSystem/observation-category"
              }
            ]
          },
          {
            "coding": [
              {
                "code": "GE",
                "system": "http://terminology.hl7.org/CodeSystem/v2-0074"
              }
            ]
          }
        ],
        "code": {
          "coding": [
            {
              "code": "Has-consent-been-obtained-for-tests?",
              "display": "Y"
            }
          ]
        },
        "performer": [
          {
            "identifier": {
              "system": "https://fhir.nhs.uk/Id/ods-organization-code",
              "value": "699X0"
            },
            "type": "Organization"
          }
        ],
        "status": "final",
        "subject": {
          "reference": "urn:uuid:3dda2513-de5d-47fd-a734-bc31c6a623d6"
        }
      }
    },
    {
      "fullUrl": "urn:uuid:e0419d57-e316-4ae8-8ddc-38dac0f8ed11",
      "resource": {
        "resourceType": "Observation",
        "category": [
          {
            "coding": [
              {
                "code": "laboratory",
                "system": "http://terminology.hl7.org/CodeSystem/observation-category"
              }
            ]
          },
          {
            "coding": [
              {
                "code": "GE",
                "system": "http://terminology.hl7.org/CodeSystem/v2-0074"
              }
            ]
          }
        ],
        "code": {
          "coding": [
            {
              "code": "Referring-Clinician-Email:",
              "display": "EMERSON.WONG@LWH.NHS.UK"
            }
          ]
        },
        "performer": [
          {
            "identifier": {
              "system": "https://fhir.nhs.uk/Id/ods-organization-code",
              "value": "699X0"
            },
            "type": "Organization"
          }
        ],
        "status": "final",
        "subject": {
          "reference": "urn:uuid:3dda2513-de5d-47fd-a734-bc31c6a623d6"
        }
      }
    },
    {
      "fullUrl": "urn:uuid:9a257e71-f971-4d06-97c4-8b1572870da6",
      "resource": {
        "resourceType": "Observation",
        "category": [
          {
            "coding": [
              {
                "code": "laboratory",
                "system": "http://terminology.hl7.org/CodeSystem/observation-category"
              }
            ]
          },
          {
            "coding": [
              {
                "code": "GE",
                "system": "http://terminology.hl7.org/CodeSystem/v2-0074"
              }
            ]
          }
        ],
        "code": {
          "coding": [
            {
              "code": "Does-this-test-relate-to-an-ongoing-pregnancy?",
              "display": "N"
            }
          ]
        },
        "performer": [
          {
            "identifier": {
              "system": "https://fhir.nhs.uk/Id/ods-organization-code",
              "value": "699X0"
            },
            "type": "Organization"
          }
        ],
        "status": "final",
        "subject": {
          "reference": "urn:uuid:3dda2513-de5d-47fd-a734-bc31c6a623d6"
        }
      }
    },
    {
      "fullUrl": "urn:uuid:ae031f72-2808-473c-a03e-9b9ccda3f31a",
      "resource": {
        "resourceType": "Observation",
        "category": [
          {
            "coding": [
              {
                "code": "laboratory",
                "system": "http://terminology.hl7.org/CodeSystem/observation-category"
              }
            ]
          },
          {
            "coding": [
              {
                "code": "GE",
                "system": "http://terminology.hl7.org/CodeSystem/v2-0074"
              }
            ]
          }
        ],
        "code": {
          "coding": [
            {
              "code": "Patient-gestation:",
              "display": "2"
            }
          ]
        },
        "performer": [
          {
            "identifier": {
              "system": "https://fhir.nhs.uk/Id/ods-organization-code",
              "value": "699X0"
            },
            "type": "Organization"
          }
        ],
        "status": "final",
        "subject": {
          "reference": "urn:uuid:3dda2513-de5d-47fd-a734-bc31c6a623d6"
        }
      }
    },
    {
      "fullUrl": "urn:uuid:d6a583a5-96a5-4f0b-8536-c0a765808f40",
      "resource": {
        "resourceType": "Observation",
        "category": [
          {
            "coding": [
              {
                "code": "laboratory",
                "system": "http://terminology.hl7.org/CodeSystem/observation-category"
              }
            ]
          },
          {
            "coding": [
              {
                "code": "GE",
                "system": "http://terminology.hl7.org/CodeSystem/v2-0074"
              }
            ]
          }
        ],
        "code": {
          "coding": [
            {
              "code": "Referring-Clinician-Current-Speciality:",
              "display": "obs"
            }
          ]
        },
        "performer": [
          {
            "identifier": {
              "system": "https://fhir.nhs.uk/Id/ods-organization-code",
              "value": "699X0"
            },
            "type": "Organization"
          }
        ],
        "status": "final",
        "subject": {
          "reference": "urn:uuid:3dda2513-de5d-47fd-a734-bc31c6a623d6"
        }
      }
    },
    {
      "fullUrl": "urn:uuid:d77b21fe-46c8-4a77-8ed3-8ec8e22d20db",
      "resource": {
        "resourceType": "Observation",
        "category": [
          {
            "coding": [
              {
                "code": "laboratory",
                "system": "http://terminology.hl7.org/CodeSystem/observation-category"
              }
            ]
          },
          {
            "coding": [
              {
                "code": "GE",
                "system": "http://terminology.hl7.org/CodeSystem/v2-0074"
              }
            ]
          }
        ],
        "code": {
          "coding": [
            {
              "code": "Patient-is-from-consanguineous-union?",
              "display": "Unknown"
            }
          ]
        },
        "performer": [
          {
            "identifier": {
              "system": "https://fhir.nhs.uk/Id/ods-organization-code",
              "value": "699X0"
            },
            "type": "Organization"
          }
        ],
        "status": "final",
        "subject": {
          "reference": "urn:uuid:3dda2513-de5d-47fd-a734-bc31c6a623d6"
        }
      }
    },
    {
      "fullUrl": "urn:uuid:f0481cc5-0d9a-43bf-86eb-d2b24354df9f",
      "resource": {
        "resourceType": "Observation",
        "category": [
          {
            "coding": [
              {
                "code": "laboratory",
                "system": "http://terminology.hl7.org/CodeSystem/observation-category"
              }
            ]
          },
          {
            "coding": [
              {
                "code": "GE",
                "system": "http://terminology.hl7.org/CodeSystem/v2-0074"
              }
            ]
          }
        ],
        "code": {
          "coding": [
            {
              "code": "Referring-Organisation-ODS-code:",
              "display": "Liverpool Women's Hospital"
            }
          ]
        },
        "performer": [
          {
            "identifier": {
              "system": "https://fhir.nhs.uk/Id/ods-organization-code",
              "value": "699X0"
            },
            "type": "Organization"
          }
        ],
        "status": "final",
        "subject": {
          "reference": "urn:uuid:3dda2513-de5d-47fd-a734-bc31c6a623d6"
        }
      }
    },
    {
      "fullUrl": "urn:uuid:406ce743-5f36-4608-abfd-0e44d29fb906",
      "resource": {
        "resourceType": "Observation",
        "category": [
          {
            "coding": [
              {
                "code": "laboratory",
                "system": "http://terminology.hl7.org/CodeSystem/observation-category"
              }
            ]
          },
          {
            "coding": [
              {
                "code": "GE",
                "system": "http://terminology.hl7.org/CodeSystem/v2-0074"
              }
            ]
          }
        ],
        "code": {
          "coding": [
            {
              "code": "Secondary-Clinician-Email:",
              "display": "EMERSON.WONG@LWH.NHS.UK"
            }
          ]
        },
        "performer": [
          {
            "identifier": {
              "system": "https://fhir.nhs.uk/Id/ods-organization-code",
              "value": "699X0"
            },
            "type": "Organization"
          }
        ],
        "status": "final",
        "subject": {
          "reference": "urn:uuid:3dda2513-de5d-47fd-a734-bc31c6a623d6"
        }
      }
    },
    {
      "fullUrl": "urn:uuid:713d051b-d917-4134-b25d-b852eee5cec7",
      "resource": {
        "resourceType": "Observation",
        "category": [
          {
            "coding": [
              {
                "code": "laboratory",
                "system": "http://terminology.hl7.org/CodeSystem/observation-category"
              }
            ]
          },
          {
            "coding": [
              {
                "code": "GE",
                "system": "http://terminology.hl7.org/CodeSystem/v2-0074"
              }
            ]
          }
        ],
        "code": {
          "coding": [
            {
              "code": "Does-this-test-relate-to-a-pregnancy-with->-1-fetus?",
              "display": "N"
            }
          ]
        },
        "performer": [
          {
            "identifier": {
              "system": "https://fhir.nhs.uk/Id/ods-organization-code",
              "value": "699X0"
            },
            "type": "Organization"
          }
        ],
        "status": "final",
        "subject": {
          "reference": "urn:uuid:3dda2513-de5d-47fd-a734-bc31c6a623d6"
        }
      }
    },
    {
      "fullUrl": "urn:uuid:0ba88283-1428-44fa-ad7b-12d03e858592",
      "resource": {
        "resourceType": "Observation",
        "category": [
          {
            "coding": [
              {
                "code": "laboratory",
                "system": "http://terminology.hl7.org/CodeSystem/observation-category"
              }
            ]
          },
          {
            "coding": [
              {
                "code": "GE",
                "system": "http://terminology.hl7.org/CodeSystem/v2-0074"
              }
            ]
          }
        ],
        "code": {
          "coding": [
            {
              "code": "Is-this-test-for-a-decreased-infant-or-pregnancy-loss?",
              "display": "Yes"
            }
          ]
        },
        "performer": [
          {
            "identifier": {
              "system": "https://fhir.nhs.uk/Id/ods-organization-code",
              "value": "699X0"
            },
            "type": "Organization"
          }
        ],
        "status": "final",
        "subject": {
          "reference": "urn:uuid:3dda2513-de5d-47fd-a734-bc31c6a623d6"
        }
      }
    },
    {
      "fullUrl": "urn:uuid:c114f0a5-a23f-4da8-8439-973d25fd4cb7",
      "resource": {
        "resourceType": "Observation",
        "category": [
          {
            "coding": [
              {
                "code": "laboratory",
                "system": "http://terminology.hl7.org/CodeSystem/observation-category"
              }
            ]
          },
          {
            "coding": [
              {
                "code": "GE",
                "system": "http://terminology.hl7.org/CodeSystem/v2-0074"
              }
            ]
          }
        ],
        "code": {
          "coding": [
            {
              "code": "Patient-expected-delivery-date:",
              "display": "06/11/25"
            }
          ]
        },
        "performer": [
          {
            "identifier": {
              "system": "https://fhir.nhs.uk/Id/ods-organization-code",
              "value": "699X0"
            },
            "type": "Organization"
          }
        ],
        "status": "final",
        "subject": {
          "reference": "urn:uuid:3dda2513-de5d-47fd-a734-bc31c6a623d6"
        }
      }
    },
    {
      "fullUrl": "urn:uuid:b60b68e8-5191-4c36-82e1-1214b07c72c5",
      "resource": {
        "resourceType": "Observation",
        "category": [
          {
            "coding": [
              {
                "code": "laboratory",
                "system": "http://terminology.hl7.org/CodeSystem/observation-category"
              }
            ]
          },
          {
            "coding": [
              {
                "code": "GE",
                "system": "http://terminology.hl7.org/CodeSystem/v2-0074"
              }
            ]
          }
        ],
        "code": {
          "coding": [
            {
              "code": "Is-the-test-done-in-the-prenatal-or-neonatal-period?",
              "display": "Neonatal"
            }
          ]
        },
        "performer": [
          {
            "identifier": {
              "system": "https://fhir.nhs.uk/Id/ods-organization-code",
              "value": "699X0"
            },
            "type": "Organization"
          }
        ],
        "status": "final",
        "subject": {
          "reference": "urn:uuid:3dda2513-de5d-47fd-a734-bc31c6a623d6"
        }
      }
    },
    {
      "fullUrl": "urn:uuid:5c965b28-0553-4eea-b9dc-8e67423c7c43",
      "resource": {
        "resourceType": "Observation",
        "category": [
          {
            "coding": [
              {
                "code": "laboratory",
                "system": "http://terminology.hl7.org/CodeSystem/observation-category"
              }
            ]
          },
          {
            "coding": [
              {
                "code": "GE",
                "system": "http://terminology.hl7.org/CodeSystem/v2-0074"
              }
            ]
          }
        ],
        "code": {
          "coding": [
            {
              "code": "Referring-Clinician-Name:",
              "display": "emerson wong"
            }
          ]
        },
        "performer": [
          {
            "identifier": {
              "system": "https://fhir.nhs.uk/Id/ods-organization-code",
              "value": "699X0"
            },
            "type": "Organization"
          }
        ],
        "status": "final",
        "subject": {
          "reference": "urn:uuid:3dda2513-de5d-47fd-a734-bc31c6a623d6"
        }
      }
    },
    {
      "fullUrl": "urn:uuid:910ee560-5998-47df-aa80-02b7befff1b3",
      "resource": {
        "resourceType": "Observation",
        "category": [
          {
            "coding": [
              {
                "code": "laboratory",
                "system": "http://terminology.hl7.org/CodeSystem/observation-category"
              }
            ]
          },
          {
            "coding": [
              {
                "code": "GE",
                "system": "http://terminology.hl7.org/CodeSystem/v2-0074"
              }
            ]
          }
        ],
        "code": {
          "text": "Unknown observation code"
        },
        "performer": [
          {
            "identifier": {
              "system": "https://fhir.nhs.uk/Id/ods-organization-code",
              "value": "699X0"
            },
            "type": "Organization"
          }
        ],
        "status": "final",
        "subject": {
          "reference": "urn:uuid:3dda2513-de5d-47fd-a734-bc31c6a623d6"
        }
      }
    },
    {
      "fullUrl": "urn:uuid:6159480e-4d5d-454d-b89c-4bb7e04d4870",
      "resource": {
        "resourceType": "Specimen",
        "status": "unavailable",
        "subject": {
          "reference": "urn:uuid:3dda2513-de5d-47fd-a734-bc31c6a623d6"
        }
      }
    },
    {
      "fullUrl": "urn:uuid:40e1b2cf-8e51-4478-b929-3c06be2e3a4e",
      "resource": {
        "resourceType": "ServiceRequest",
        "authoredOn": "2025-11-06T13:53:39+00:00",
        "category": [
          {
            "coding": [
              {
                "code": "116148004",
                "system": "http://snomed.info/sct"
              }
            ]
          }
        ],
        "code": {
          "coding": [
            {
              "code": "R250.1",
              "system": "https://fhir.nhs.uk/CodeSystem/England-GenomicTestDirectory"
            }
          ]
        },
        "encounter": {
          "identifier": {
            "assigner": {
              "identifier": {
                "system": "https://fhir.nhs.uk/Id/ods-organization-code",
                "value": "REP"
              }
            },
            "type": {
              "coding": [
                {
                  "code": "VN",
                  "system": "http://terminology.hl7.org/CodeSystem/v2-0203"
                }
              ]
            },
            "value": "L00000073528"
          },
          "reference": "urn:uuid:47f4c2b8-f2b5-4e2b-a9b0-e3aecd6d33c3"
        },
        "intent": "order",
        "specimen": [
          {
            "reference": "urn:uuid:6159480e-4d5d-454d-b89c-4bb7e04d4870",
            "type": "Specimen"
          }
        ],
        "status": "active",
        "subject": {
          "reference": "urn:uuid:3dda2513-de5d-47fd-a734-bc31c6a623d6"
        },
        "supportingInfo": [
          {
            "reference": "urn:uuid:a06eccb2-7b6c-46a9-a1a2-8ecf863d6b54",
            "type": "Observation"
          },
          {
            "reference": "urn:uuid:66f2cdb5-4422-487b-9b18-8f305ceab5f5",
            "type": "Observation"
          },
          {
            "reference": "urn:uuid:5d85f321-ebe7-48b8-ac6c-6b9299023cf2",
            "type": "Observation"
          },
          {
            "reference": "urn:uuid:e0419d57-e316-4ae8-8ddc-38dac0f8ed11",
            "type": "Observation"
          },
          {
            "reference": "urn:uuid:9a257e71-f971-4d06-97c4-8b1572870da6",
            "type": "Observation"
          },
          {
            "reference": "urn:uuid:ae031f72-2808-473c-a03e-9b9ccda3f31a",
            "type": "Observation"
          },
          {
            "reference": "urn:uuid:d6a583a5-96a5-4f0b-8536-c0a765808f40",
            "type": "Observation"
          },
          {
            "reference": "urn:uuid:d77b21fe-46c8-4a77-8ed3-8ec8e22d20db",
            "type": "Observation"
          },
          {
            "reference": "urn:uuid:f0481cc5-0d9a-43bf-86eb-d2b24354df9f",
            "type": "Observation"
          },
          {
            "reference": "urn:uuid:406ce743-5f36-4608-abfd-0e44d29fb906",
            "type": "Observation"
          },
          {
            "reference": "urn:uuid:713d051b-d917-4134-b25d-b852eee5cec7",
            "type": "Observation"
          },
          {
            "reference": "urn:uuid:0ba88283-1428-44fa-ad7b-12d03e858592",
            "type": "Observation"
          },
          {
            "reference": "urn:uuid:c114f0a5-a23f-4da8-8439-973d25fd4cb7",
            "type": "Observation"
          },
          {
            "reference": "urn:uuid:b60b68e8-5191-4c36-82e1-1214b07c72c5",
            "type": "Observation"
          },
          {
            "reference": "urn:uuid:5c965b28-0553-4eea-b9dc-8e67423c7c43",
            "type": "Observation"
          },
          {
            "reference": "urn:uuid:910ee560-5998-47df-aa80-02b7befff1b3",
            "type": "Observation"
          }
        ]
      }
    }
  ],
  "identifier": {
    "value": "b4130d36-79d8-4b27-9813-418ab2e3a30d"
  },
  "timestamp": "2026-02-02T22:18:41+00:00",
  "type": "message"
}