{
  "resourceType": "Bundle",
  "entry": [
    {
      "fullUrl": "urn:uuid:52270c0a-6b68-443e-9f09-8acf96acc780",
      "resource": {
        "resourceType": "MessageHeader",
        "destination": [
          {
            "endpoint": "https//fhir.mft.nhs.uk/Endpoint/LIMS",
            "receiver": {
              "identifier": {
                "system": "https://fhir.nhs.uk/Id/ods-organization-code",
                "value": "699X0"
              }
            }
          }
        ],
        "eventCoding": {
          "code": "O21",
          "system": "http://terminology.hl7.org/CodeSystem/v2-0003"
        },
        "focus": [
          {
            "reference": "urn:uuid:181c9487-dec5-4a45-91eb-bcf16cf55b0f"
          }
        ],
        "sender": {
          "identifier": {
            "system": "https://fhir.nhs.uk/Id/ods-organization-code",
            "value": "R0A"
          }
        },
        "source": {
          "endpoint": "https://fhir.nwgenomics.nhs.uk/Endpoint/HIVE",
          "software": "NW GLH"
        }
      }
    },
    {
      "fullUrl": "urn:uuid:4ca1afff-154e-4f42-91c0-a9b3b05b3212",
      "resource": {
        "resourceType": "Patient",
        "address": [
          {
            "postalCode": "M13 9PL"
          }
        ],
        "birthDate": "1972-09-21",
        "gender": "female",
        "identifier": [
          {
            "extension": [
              {
                "url": "https://fhir.hl7.org.uk/StructureDefinition/Extension-UKCore-NHSNumberVerificationStatus",
                "valueCodeableConcept": {
                  "coding": [
                    {
                      "code": "05",
                      "display": "Trace needs to be resolved - (NHS number or patient detail conflict)",
                      "system": "https://fhir.hl7.org.uk/CodeSystem/UKCore-NHSNumberVerificationStatusEngland"
                    }
                  ]
                }
              }
            ],
            "system": "https://fhir.nhs.uk/Id/nhs-number",
            "type": {
              "coding": [
                {
                  "code": "NH",
                  "system": "http://terminology.hl7.org/CodeSystem/v2-0203"
                }
              ]
            },
            "value": "9737383192"
          },
          {
            "assigner": {
              "identifier": {
                "system": "https://fhir.nhs.uk/Id/ods-organization-code",
                "value": "R0A"
              }
            },
            "system": "urn:oid:1.2.840.114350.1.13.611.3.7.5.737384.14",
            "type": {
              "coding": [
                {
                  "code": "MR",
                  "system": "http://terminology.hl7.org/CodeSystem/v2-0203"
                }
              ]
            },
            "value": "1234567"
          }
        ],
        "name": [
          {
            "family": "MANCHESTER",
            "given": [
              "SANSA"
            ]
          }
        ]
      }
    },
    {
      "fullUrl": "urn:uuid:4d07344b-8f8a-4a01-8b95-867607d6e5d1",
      "resource": {
        "resourceType": "Encounter",
        "class": {
          "code": "OBSENC",
          "system": "http://terminology.hl7.org/CodeSystem/v3-ActCode"
        },
        "identifier": [
          {
            "assigner": {
              "identifier": {
                "system": "https://fhir.nhs.uk/Id/ods-organization-code",
                "value": "R0A"
              }
            },
            "type": {
              "coding": [
                {
                  "code": "VN",
                  "system": "http://terminology.hl7.org/CodeSystem/v2-0203"
                }
              ]
            },
            "value": "1001166717"
          }
        ],
        "location": [
          {
            "location": {
              "identifier": {
                "value": "^^^R0A09^^^^^^^R0A"
              }
            }
          }
        ],
        "serviceType": {
          "coding": [
            {
              "code": "100"
            }
          ]
        },
        "status": "finished",
        "subject": {
          "identifier": {
            "system": "https://fhir.nhs.uk/Id/nhs-number",
            "type": {
              "coding": [
                {
                  "code": "NH",
                  "system": "http://terminology.hl7.org/CodeSystem/v2-0203"
                }
              ]
            },
            "value": "9737383192"
          },
          "reference": "urn:uuid:4ca1afff-154e-4f42-91c0-a9b3b05b3212"
        }
      }
    },
    {
      "fullUrl": "urn:uuid:fa4c9345-6d89-4916-8fd3-a04c27f8dc1d",
      "resource": {
        "resourceType": "PractitionerRole",
        "organization": {
          "display": "Manchester University NHS Foundation Trust",
          "identifier": {
            "system": "https://fhir.nhs.uk/Id/ods-organization-code",
            "value": "R0A"
          }
        },
        "practitioner": {
          "display": "Darwin, Samuel",
          "identifier": {
            "system": "https://fhir.hl7.org.uk/Id/gmc-number",
            "value": "C3456789"
          }
        }
      }
    },
    {
      "fullUrl": "urn:uuid:5a552148-10d7-4b4c-9ffc-89951cf9a25e",
      "resource": {
        "resourceType": "Observation",
        "code": {
          "coding": [
            {
              "code": "GENEAP",
              "display": "GENETICS TEST PERFORMABLE",
              "system": "https://fhir.nwgenomics.nhs.uk/CodeSystem/NWGMSA"
            }
          ]
        },
        "effectiveDateTime": "2025-01-29T10:37:26+00:00",
        "identifier": [
          {
            "assigner": {
              "identifier": {
                "system": "https://fhir.nhs.uk/Id/ods-organization-code",
                "value": "ROA"
              }
            },
            "system": "urn:oid:1.2.840.114350.1.13.861.1.7.2.798268",
            "type": {
              "coding": [
                {
                  "code": "PLAC",
                  "system": "http://terminology.hl7.org/CodeSystem/v2-0203"
                }
              ]
            },
            "value": "1601716017"
          },
          {
            "assigner": {
              "identifier": {
                "system": "https://fhir.nhs.uk/Id/ods-organization-code",
                "value": "699X0"
              }
            },
            "system": "http://www.acme.org/servicerequest",
            "type": {
              "coding": [
                {
                  "code": "FILL",
                  "system": "http://terminology.hl7.org/CodeSystem/v2-0203"
                }
              ]
            },
            "value": "1001166717"
          }
        ],
        "performer": [
          {
            "identifier": {
              "system": "https://fhir.nhs.uk/Id/ods-organization-code",
              "value": "699X0"
            },
            "type": "Organization"
          }
        ],
        "status": "final",
        "subject": {
          "identifier": {
            "system": "https://fhir.nhs.uk/Id/nhs-number",
            "type": {
              "coding": [
                {
                  "code": "NH",
                  "system": "http://terminology.hl7.org/CodeSystem/v2-0203"
                }
              ]
            },
            "value": "9737383192"
          },
          "reference": "urn:uuid:4ca1afff-154e-4f42-91c0-a9b3b05b3212"
        }
      }
    },
    {
      "fullUrl": "urn:uuid:196a7c86-dbbd-4e10-8fec-a63172aae3d4",
      "resource": {
        "resourceType": "Observation",
        "code": {
          "coding": [
            {
              "code": "230056",
              "display": "What Type of Referral Do You Require?",
              "system": "https://fhir.nwgenomics.nhs.uk/CodeSystem/NWGMSA"
            }
          ]
        },
        "effectiveDateTime": "2025-01-29T10:37:26+00:00",
        "identifier": [
          {
            "assigner": {
              "identifier": {
                "system": "https://fhir.nhs.uk/Id/ods-organization-code",
                "value": "ROA"
              }
            },
            "system": "urn:oid:1.2.840.114350.1.13.861.1.7.2.798268",
            "type": {
              "coding": [
                {
                  "code": "PLAC",
                  "system": "http://terminology.hl7.org/CodeSystem/v2-0203"
                }
              ]
            },
            "value": "1601716017"
          },
          {
            "assigner": {
              "identifier": {
                "system": "https://fhir.nhs.uk/Id/ods-organization-code",
                "value": "699X0"
              }
            },
            "system": "http://www.acme.org/servicerequest",
            "type": {
              "coding": [
                {
                  "code": "FILL",
                  "system": "http://terminology.hl7.org/CodeSystem/v2-0203"
                }
              ]
            },
            "value": "1001166717"
          }
        ],
        "performer": [
          {
            "identifier": {
              "system": "https://fhir.nhs.uk/Id/ods-organization-code",
              "value": "699X0"
            },
            "type": "Organization"
          }
        ],
        "status": "final",
        "subject": {
          "identifier": {
            "system": "https://fhir.nhs.uk/Id/nhs-number",
            "type": {
              "coding": [
                {
                  "code": "NH",
                  "system": "http://terminology.hl7.org/CodeSystem/v2-0203"
                }
              ]
            },
            "value": "9737383192"
          },
          "reference": "urn:uuid:4ca1afff-154e-4f42-91c0-a9b3b05b3212"
        },
        "valueCodeableConcept": {
          "coding": [
            {
              "code": "1186936003",
              "display": "Storage of specimen (procedure)",
              "system": "http://snomed.info/sct"
            }
          ]
        }
      }
    },
    {
      "fullUrl": "urn:uuid:731542e9-f46f-4c55-afeb-77587f217842",
      "resource": {
        "resourceType": "Observation",
        "code": {
          "coding": [
            {
              "code": "281269004",
              "display": "High infection risk sample",
              "system": "http://snomed.info/sct"
            }
          ]
        },
        "effectiveDateTime": "2025-01-29T10:37:26+00:00",
        "identifier": [
          {
            "assigner": {
              "identifier": {
                "system": "https://fhir.nhs.uk/Id/ods-organization-code",
                "value": "ROA"
              }
            },
            "system": "urn:oid:1.2.840.114350.1.13.861.1.7.2.798268",
            "type": {
              "coding": [
                {
                  "code": "PLAC",
                  "system": "http://terminology.hl7.org/CodeSystem/v2-0203"
                }
              ]
            },
            "value": "1601716017"
          },
          {
            "assigner": {
              "identifier": {
                "system": "https://fhir.nhs.uk/Id/ods-organization-code",
                "value": "699X0"
              }
            },
            "system": "http://www.acme.org/servicerequest",
            "type": {
              "coding": [
                {
                  "code": "FILL",
                  "system": "http://terminology.hl7.org/CodeSystem/v2-0203"
                }
              ]
            },
            "value": "1001166717"
          }
        ],
        "performer": [
          {
            "identifier": {
              "system": "https://fhir.nhs.uk/Id/ods-organization-code",
              "value": "699X0"
            },
            "type": "Organization"
          }
        ],
        "status": "final",
        "subject": {
          "identifier": {
            "system": "https://fhir.nhs.uk/Id/nhs-number",
            "type": {
              "coding": [
                {
                  "code": "NH",
                  "system": "http://terminology.hl7.org/CodeSystem/v2-0203"
                }
              ]
            },
            "value": "9737383192"
          },
          "reference": "urn:uuid:4ca1afff-154e-4f42-91c0-a9b3b05b3212"
        },
        "valueCodeableConcept": {
          "coding": [
            {
              "code": "LA32-8",
              "display": "No",
              "system": "http://loinc.org"
            }
          ]
        }
      }
    },
    {
      "fullUrl": "urn:uuid:b90062d3-acba-4286-a2f1-83cb9e9014ea",
      "resource": {
        "resourceType": "Observation",
        "code": {
          "coding": [
            {
              "code": "230016",
              "display": "Test Type",
              "system": "https://fhir.nwgenomics.nhs.uk/CodeSystem/NWGMSA"
            }
          ]
        },
        "effectiveDateTime": "2025-01-29T10:37:26+00:00",
        "identifier": [
          {
            "assigner": {
              "identifier": {
                "system": "https://fhir.nhs.uk/Id/ods-organization-code",
                "value": "ROA"
              }
            },
            "system": "urn:oid:1.2.840.114350.1.13.861.1.7.2.798268",
            "type": {
              "coding": [
                {
                  "code": "PLAC",
                  "system": "http://terminology.hl7.org/CodeSystem/v2-0203"
                }
              ]
            },
            "value": "1601716017"
          },
          {
            "assigner": {
              "identifier": {
                "system": "https://fhir.nhs.uk/Id/ods-organization-code",
                "value": "699X0"
              }
            },
            "system": "http://www.acme.org/servicerequest",
            "type": {
              "coding": [
                {
                  "code": "FILL",
                  "system": "http://terminology.hl7.org/CodeSystem/v2-0203"
                }
              ]
            },
            "value": "1001166717"
          }
        ],
        "performer": [
          {
            "identifier": {
              "system": "https://fhir.nhs.uk/Id/ods-organization-code",
              "value": "699X0"
            },
            "type": "Organization"
          }
        ],
        "status": "final",
        "subject": {
          "identifier": {
            "system": "https://fhir.nhs.uk/Id/nhs-number",
            "type": {
              "coding": [
                {
                  "code": "NH",
                  "system": "http://terminology.hl7.org/CodeSystem/v2-0203"
                }
              ]
            },
            "value": "9737383192"
          },
          "reference": "urn:uuid:4ca1afff-154e-4f42-91c0-a9b3b05b3212"
        },
        "valueString": "Diagnostic Screen/Test"
      }
    },
    {
      "fullUrl": "urn:uuid:0263020b-3463-44e7-9602-95ab0bcc162b",
      "resource": {
        "resourceType": "Observation",
        "code": {
          "coding": [
            {
              "code": "77386006",
              "display": "Pregnancy",
              "system": "http://snomed.info/sct"
            }
          ]
        },
        "effectiveDateTime": "2025-01-29T10:37:26+00:00",
        "identifier": [
          {
            "assigner": {
              "identifier": {
                "system": "https://fhir.nhs.uk/Id/ods-organization-code",
                "value": "ROA"
              }
            },
            "system": "urn:oid:1.2.840.114350.1.13.861.1.7.2.798268",
            "type": {
              "coding": [
                {
                  "code": "PLAC",
                  "system": "http://terminology.hl7.org/CodeSystem/v2-0203"
                }
              ]
            },
            "value": "1601716017"
          },
          {
            "assigner": {
              "identifier": {
                "system": "https://fhir.nhs.uk/Id/ods-organization-code",
                "value": "699X0"
              }
            },
            "system": "http://www.acme.org/servicerequest",
            "type": {
              "coding": [
                {
                  "code": "FILL",
                  "system": "http://terminology.hl7.org/CodeSystem/v2-0203"
                }
              ]
            },
            "value": "1001166717"
          }
        ],
        "performer": [
          {
            "identifier": {
              "system": "https://fhir.nhs.uk/Id/ods-organization-code",
              "value": "699X0"
            },
            "type": "Organization"
          }
        ],
        "status": "final",
        "subject": {
          "identifier": {
            "system": "https://fhir.nhs.uk/Id/nhs-number",
            "type": {
              "coding": [
                {
                  "code": "NH",
                  "system": "http://terminology.hl7.org/CodeSystem/v2-0203"
                }
              ]
            },
            "value": "9737383192"
          },
          "reference": "urn:uuid:4ca1afff-154e-4f42-91c0-a9b3b05b3212"
        },
        "valueCodeableConcept": {
          "coding": [
            {
              "code": "LA33-6",
              "display": "Yes",
              "system": "http://loinc.org"
            }
          ]
        }
      }
    },
    {
      "fullUrl": "urn:uuid:9ddcbd55-5219-43f9-9b3a-925b9e00c5b4",
      "resource": {
        "resourceType": "Observation",
        "code": {
          "coding": [
            {
              "code": "231284",
              "display": "Please Select R240 Test(s):",
              "system": "https://fhir.nwgenomics.nhs.uk/CodeSystem/NWGMSA"
            }
          ]
        },
        "effectiveDateTime": "2025-01-29T10:37:26+00:00",
        "identifier": [
          {
            "assigner": {
              "identifier": {
                "system": "https://fhir.nhs.uk/Id/ods-organization-code",
                "value": "ROA"
              }
            },
            "system": "urn:oid:1.2.840.114350.1.13.861.1.7.2.798268",
            "type": {
              "coding": [
                {
                  "code": "PLAC",
                  "system": "http://terminology.hl7.org/CodeSystem/v2-0203"
                }
              ]
            },
            "value": "1601716017"
          },
          {
            "assigner": {
              "identifier": {
                "system": "https://fhir.nhs.uk/Id/ods-organization-code",
                "value": "699X0"
              }
            },
            "system": "http://www.acme.org/servicerequest",
            "type": {
              "coding": [
                {
                  "code": "FILL",
                  "system": "http://terminology.hl7.org/CodeSystem/v2-0203"
                }
              ]
            },
            "value": "1001166717"
          }
        ],
        "performer": [
          {
            "identifier": {
              "system": "https://fhir.nhs.uk/Id/ods-organization-code",
              "value": "699X0"
            },
            "type": "Organization"
          }
        ],
        "status": "final",
        "subject": {
          "identifier": {
            "system": "https://fhir.nhs.uk/Id/nhs-number",
            "type": {
              "coding": [
                {
                  "code": "NH",
                  "system": "http://terminology.hl7.org/CodeSystem/v2-0203"
                }
              ]
            },
            "value": "9737383192"
          },
          "reference": "urn:uuid:4ca1afff-154e-4f42-91c0-a9b3b05b3212"
        },
        "valueString": "R240.1: Targeted variant testing"
      }
    },
    {
      "fullUrl": "urn:uuid:8cf333e6-81bb-402d-a3c5-1a202a6a464e",
      "resource": {
        "resourceType": "Observation",
        "code": {
          "coding": [
            {
              "code": "231285",
              "display": "Please Select R242 Test(s):",
              "system": "https://fhir.nwgenomics.nhs.uk/CodeSystem/NWGMSA"
            }
          ]
        },
        "effectiveDateTime": "2025-01-29T10:37:26+00:00",
        "identifier": [
          {
            "assigner": {
              "identifier": {
                "system": "https://fhir.nhs.uk/Id/ods-organization-code",
                "value": "ROA"
              }
            },
            "system": "urn:oid:1.2.840.114350.1.13.861.1.7.2.798268",
            "type": {
              "coding": [
                {
                  "code": "PLAC",
                  "system": "http://terminology.hl7.org/CodeSystem/v2-0203"
                }
              ]
            },
            "value": "1601716017"
          },
          {
            "assigner": {
              "identifier": {
                "system": "https://fhir.nhs.uk/Id/ods-organization-code",
                "value": "699X0"
              }
            },
            "system": "http://www.acme.org/servicerequest",
            "type": {
              "coding": [
                {
                  "code": "FILL",
                  "system": "http://terminology.hl7.org/CodeSystem/v2-0203"
                }
              ]
            },
            "value": "1001166717"
          }
        ],
        "performer": [
          {
            "identifier": {
              "system": "https://fhir.nhs.uk/Id/ods-organization-code",
              "value": "699X0"
            },
            "type": "Organization"
          }
        ],
        "status": "final",
        "subject": {
          "identifier": {
            "system": "https://fhir.nhs.uk/Id/nhs-number",
            "type": {
              "coding": [
                {
                  "code": "NH",
                  "system": "http://terminology.hl7.org/CodeSystem/v2-0203"
                }
              ]
            },
            "value": "9737383192"
          },
          "reference": "urn:uuid:4ca1afff-154e-4f42-91c0-a9b3b05b3212"
        },
        "valueString": "R242.1: Targeted variant testing"
      }
    },
    {
      "fullUrl": "urn:uuid:e317f624-ef13-4749-8fc2-4e3d38216735",
      "resource": {
        "resourceType": "Observation",
        "code": {
          "coding": [
            {
              "code": "230027",
              "display": "Email Addresses of Non-MFT Clinicians for Result Reports",
              "system": "https://fhir.nwgenomics.nhs.uk/CodeSystem/NWGMSA"
            }
          ]
        },
        "effectiveDateTime": "2025-01-29T10:37:26+00:00",
        "identifier": [
          {
            "assigner": {
              "identifier": {
                "system": "https://fhir.nhs.uk/Id/ods-organization-code",
                "value": "ROA"
              }
            },
            "system": "urn:oid:1.2.840.114350.1.13.861.1.7.2.798268",
            "type": {
              "coding": [
                {
                  "code": "PLAC",
                  "system": "http://terminology.hl7.org/CodeSystem/v2-0203"
                }
              ]
            },
            "value": "1601716017"
          },
          {
            "assigner": {
              "identifier": {
                "system": "https://fhir.nhs.uk/Id/ods-organization-code",
                "value": "699X0"
              }
            },
            "system": "http://www.acme.org/servicerequest",
            "type": {
              "coding": [
                {
                  "code": "FILL",
                  "system": "http://terminology.hl7.org/CodeSystem/v2-0203"
                }
              ]
            },
            "value": "1001166717"
          }
        ],
        "performer": [
          {
            "identifier": {
              "system": "https://fhir.nhs.uk/Id/ods-organization-code",
              "value": "699X0"
            },
            "type": "Organization"
          }
        ],
        "status": "final",
        "subject": {
          "identifier": {
            "system": "https://fhir.nhs.uk/Id/nhs-number",
            "type": {
              "coding": [
                {
                  "code": "NH",
                  "system": "http://terminology.hl7.org/CodeSystem/v2-0203"
                }
              ]
            },
            "value": "9737383192"
          },
          "reference": "urn:uuid:4ca1afff-154e-4f42-91c0-a9b3b05b3212"
        },
        "valueString": "charu"
      }
    },
    {
      "fullUrl": "urn:uuid:cd115645-195e-4a3b-a1a6-d4e6a55591a0",
      "resource": {
        "resourceType": "Observation",
        "code": {
          "coding": [
            {
              "code": "762911000000102",
              "display": "Informed consent given for treatment",
              "system": "http://snomed.info/sct"
            }
          ]
        },
        "effectiveDateTime": "2025-01-29T10:37:26+00:00",
        "identifier": [
          {
            "assigner": {
              "identifier": {
                "system": "https://fhir.nhs.uk/Id/ods-organization-code",
                "value": "ROA"
              }
            },
            "system": "urn:oid:1.2.840.114350.1.13.861.1.7.2.798268",
            "type": {
              "coding": [
                {
                  "code": "PLAC",
                  "system": "http://terminology.hl7.org/CodeSystem/v2-0203"
                }
              ]
            },
            "value": "1601716017"
          },
          {
            "assigner": {
              "identifier": {
                "system": "https://fhir.nhs.uk/Id/ods-organization-code",
                "value": "699X0"
              }
            },
            "system": "http://www.acme.org/servicerequest",
            "type": {
              "coding": [
                {
                  "code": "FILL",
                  "system": "http://terminology.hl7.org/CodeSystem/v2-0203"
                }
              ]
            },
            "value": "1001166717"
          }
        ],
        "performer": [
          {
            "identifier": {
              "system": "https://fhir.nhs.uk/Id/ods-organization-code",
              "value": "699X0"
            },
            "type": "Organization"
          }
        ],
        "status": "final",
        "subject": {
          "identifier": {
            "system": "https://fhir.nhs.uk/Id/nhs-number",
            "type": {
              "coding": [
                {
                  "code": "NH",
                  "system": "http://terminology.hl7.org/CodeSystem/v2-0203"
                }
              ]
            },
            "value": "9737383192"
          },
          "reference": "urn:uuid:4ca1afff-154e-4f42-91c0-a9b3b05b3212"
        },
        "valueCodeableConcept": {
          "coding": [
            {
              "code": "LA33-6",
              "display": "Yes",
              "system": "http://loinc.org"
            }
          ]
        }
      }
    },
    {
      "fullUrl": "urn:uuid:87b7b2cf-dde8-4950-a246-3b32e075ecd5",
      "resource": {
        "resourceType": "Observation",
        "code": {
          "coding": [
            {
              "code": "230037",
              "display": "Please Acknowledge That a DNA Sample Will be Stored in the Laboratory on Completion of Testing",
              "system": "https://fhir.nwgenomics.nhs.uk/CodeSystem/NWGMSA"
            }
          ]
        },
        "effectiveDateTime": "2025-01-29T10:37:26+00:00",
        "identifier": [
          {
            "assigner": {
              "identifier": {
                "system": "https://fhir.nhs.uk/Id/ods-organization-code",
                "value": "ROA"
              }
            },
            "system": "urn:oid:1.2.840.114350.1.13.861.1.7.2.798268",
            "type": {
              "coding": [
                {
                  "code": "PLAC",
                  "system": "http://terminology.hl7.org/CodeSystem/v2-0203"
                }
              ]
            },
            "value": "1601716017"
          },
          {
            "assigner": {
              "identifier": {
                "system": "https://fhir.nhs.uk/Id/ods-organization-code",
                "value": "699X0"
              }
            },
            "system": "http://www.acme.org/servicerequest",
            "type": {
              "coding": [
                {
                  "code": "FILL",
                  "system": "http://terminology.hl7.org/CodeSystem/v2-0203"
                }
              ]
            },
            "value": "1001166717"
          }
        ],
        "performer": [
          {
            "identifier": {
              "system": "https://fhir.nhs.uk/Id/ods-organization-code",
              "value": "699X0"
            },
            "type": "Organization"
          }
        ],
        "status": "final",
        "subject": {
          "identifier": {
            "system": "https://fhir.nhs.uk/Id/nhs-number",
            "type": {
              "coding": [
                {
                  "code": "NH",
                  "system": "http://terminology.hl7.org/CodeSystem/v2-0203"
                }
              ]
            },
            "value": "9737383192"
          },
          "reference": "urn:uuid:4ca1afff-154e-4f42-91c0-a9b3b05b3212"
        },
        "valueString": "Acknowledged"
      }
    },
    {
      "fullUrl": "urn:uuid:7f41954d-f5b5-4011-8287-2b93a37adee4",
      "resource": {
        "resourceType": "Observation",
        "code": {
          "coding": [
            {
              "code": "230039",
              "display": "Is the Person Ordering the Test the Referring Clinician",
              "system": "https://fhir.nwgenomics.nhs.uk/CodeSystem/NWGMSA"
            }
          ]
        },
        "effectiveDateTime": "2025-01-29T10:37:26+00:00",
        "identifier": [
          {
            "assigner": {
              "identifier": {
                "system": "https://fhir.nhs.uk/Id/ods-organization-code",
                "value": "ROA"
              }
            },
            "system": "urn:oid:1.2.840.114350.1.13.861.1.7.2.798268",
            "type": {
              "coding": [
                {
                  "code": "PLAC",
                  "system": "http://terminology.hl7.org/CodeSystem/v2-0203"
                }
              ]
            },
            "value": "1601716017"
          },
          {
            "assigner": {
              "identifier": {
                "system": "https://fhir.nhs.uk/Id/ods-organization-code",
                "value": "699X0"
              }
            },
            "system": "http://www.acme.org/servicerequest",
            "type": {
              "coding": [
                {
                  "code": "FILL",
                  "system": "http://terminology.hl7.org/CodeSystem/v2-0203"
                }
              ]
            },
            "value": "1001166717"
          }
        ],
        "performer": [
          {
            "identifier": {
              "system": "https://fhir.nhs.uk/Id/ods-organization-code",
              "value": "699X0"
            },
            "type": "Organization"
          }
        ],
        "status": "final",
        "subject": {
          "identifier": {
            "system": "https://fhir.nhs.uk/Id/nhs-number",
            "type": {
              "coding": [
                {
                  "code": "NH",
                  "system": "http://terminology.hl7.org/CodeSystem/v2-0203"
                }
              ]
            },
            "value": "9737383192"
          },
          "reference": "urn:uuid:4ca1afff-154e-4f42-91c0-a9b3b05b3212"
        },
        "valueString": "No"
      }
    },
    {
      "fullUrl": "urn:uuid:76eb3f66-8eb7-4ccf-ba09-545bc582a7b3",
      "resource": {
        "resourceType": "Observation",
        "code": {
          "coding": [
            {
              "code": "unknown",
              "display": "Name of Supervising Clinician",
              "system": "https://fhir.nwgenomics.nhs.uk/CodeSystem/NWGMSA"
            }
          ]
        },
        "effectiveDateTime": "2025-01-29T10:37:26+00:00",
        "identifier": [
          {
            "assigner": {
              "identifier": {
                "system": "https://fhir.nhs.uk/Id/ods-organization-code",
                "value": "ROA"
              }
            },
            "system": "urn:oid:1.2.840.114350.1.13.861.1.7.2.798268",
            "type": {
              "coding": [
                {
                  "code": "PLAC",
                  "system": "http://terminology.hl7.org/CodeSystem/v2-0203"
                }
              ]
            },
            "value": "1601716017"
          },
          {
            "assigner": {
              "identifier": {
                "system": "https://fhir.nhs.uk/Id/ods-organization-code",
                "value": "699X0"
              }
            },
            "system": "http://www.acme.org/servicerequest",
            "type": {
              "coding": [
                {
                  "code": "FILL",
                  "system": "http://terminology.hl7.org/CodeSystem/v2-0203"
                }
              ]
            },
            "value": "1001166717"
          }
        ],
        "performer": [
          {
            "identifier": {
              "system": "https://fhir.nhs.uk/Id/ods-organization-code",
              "value": "699X0"
            },
            "type": "Organization"
          }
        ],
        "status": "final",
        "subject": {
          "identifier": {
            "system": "https://fhir.nhs.uk/Id/nhs-number",
            "type": {
              "coding": [
                {
                  "code": "NH",
                  "system": "http://terminology.hl7.org/CodeSystem/v2-0203"
                }
              ]
            },
            "value": "9737383192"
          },
          "reference": "urn:uuid:4ca1afff-154e-4f42-91c0-a9b3b05b3212"
        },
        "valueString": "DESHPANDE, CHARULATA"
      }
    },
    {
      "fullUrl": "urn:uuid:d407e153-de34-4ab7-bd5a-2784e298da76",
      "resource": {
        "resourceType": "Observation",
        "code": {
          "coding": [
            {
              "code": "97209-1",
              "display": "Shipment tracking number",
              "system": "http://loinc.org"
            }
          ]
        },
        "effectiveDateTime": "2025-01-29T10:37:26+00:00",
        "identifier": [
          {
            "assigner": {
              "identifier": {
                "system": "https://fhir.nhs.uk/Id/ods-organization-code",
                "value": "ROA"
              }
            },
            "system": "urn:oid:1.2.840.114350.1.13.861.1.7.2.798268",
            "type": {
              "coding": [
                {
                  "code": "PLAC",
                  "system": "http://terminology.hl7.org/CodeSystem/v2-0203"
                }
              ]
            },
            "value": "1601716017"
          },
          {
            "assigner": {
              "identifier": {
                "system": "https://fhir.nhs.uk/Id/ods-organization-code",
                "value": "699X0"
              }
            },
            "system": "http://www.acme.org/servicerequest",
            "type": {
              "coding": [
                {
                  "code": "FILL",
                  "system": "http://terminology.hl7.org/CodeSystem/v2-0203"
                }
              ]
            },
            "value": "1001166717"
          }
        ],
        "performer": [
          {
            "identifier": {
              "system": "https://fhir.nhs.uk/Id/ods-organization-code",
              "value": "699X0"
            },
            "type": "Organization"
          }
        ],
        "status": "final",
        "subject": {
          "identifier": {
            "system": "https://fhir.nhs.uk/Id/nhs-number",
            "type": {
              "coding": [
                {
                  "code": "NH",
                  "system": "http://terminology.hl7.org/CodeSystem/v2-0203"
                }
              ]
            },
            "value": "9737383192"
          },
          "reference": "urn:uuid:4ca1afff-154e-4f42-91c0-a9b3b05b3212"
        },
        "valueString": "UK3096580215"
      }
    },
    {
      "fullUrl": "urn:uuid:3e6143ea-f443-463f-a789-d7577ba2ff84",
      "resource": {
        "resourceType": "Observation",
        "code": {
          "coding": [
            {
              "code": "842009",
              "display": "Consanguinity",
              "system": "http://snomed.info/sct"
            }
          ]
        },
        "effectiveDateTime": "2025-01-29T10:37:26+00:00",
        "identifier": [
          {
            "assigner": {
              "identifier": {
                "system": "https://fhir.nhs.uk/Id/ods-organization-code",
                "value": "ROA"
              }
            },
            "system": "urn:oid:1.2.840.114350.1.13.861.1.7.2.798268",
            "type": {
              "coding": [
                {
                  "code": "PLAC",
                  "system": "http://terminology.hl7.org/CodeSystem/v2-0203"
                }
              ]
            },
            "value": "1601716017"
          },
          {
            "assigner": {
              "identifier": {
                "system": "https://fhir.nhs.uk/Id/ods-organization-code",
                "value": "699X0"
              }
            },
            "system": "http://www.acme.org/servicerequest",
            "type": {
              "coding": [
                {
                  "code": "FILL",
                  "system": "http://terminology.hl7.org/CodeSystem/v2-0203"
                }
              ]
            },
            "value": "1001166717"
          }
        ],
        "performer": [
          {
            "identifier": {
              "system": "https://fhir.nhs.uk/Id/ods-organization-code",
              "value": "699X0"
            },
            "type": "Organization"
          }
        ],
        "status": "final",
        "subject": {
          "identifier": {
            "system": "https://fhir.nhs.uk/Id/nhs-number",
            "type": {
              "coding": [
                {
                  "code": "NH",
                  "system": "http://terminology.hl7.org/CodeSystem/v2-0203"
                }
              ]
            },
            "value": "9737383192"
          },
          "reference": "urn:uuid:4ca1afff-154e-4f42-91c0-a9b3b05b3212"
        },
        "valueCodeableConcept": {
          "coding": [
            {
              "code": "LA32-8",
              "display": "No",
              "system": "http://loinc.org"
            }
          ]
        }
      }
    },
    {
      "fullUrl": "urn:uuid:4ea646a8-86fa-4ae1-b66e-e6502b08b593",
      "resource": {
        "resourceType": "Observation",
        "code": {
          "coding": [
            {
              "code": "161714006",
              "display": "Estimated date of delivery",
              "system": "http://snomed.info/sct"
            }
          ]
        },
        "effectiveDateTime": "2025-01-29T10:37:26+00:00",
        "identifier": [
          {
            "assigner": {
              "identifier": {
                "system": "https://fhir.nhs.uk/Id/ods-organization-code",
                "value": "ROA"
              }
            },
            "system": "urn:oid:1.2.840.114350.1.13.861.1.7.2.798268",
            "type": {
              "coding": [
                {
                  "code": "PLAC",
                  "system": "http://terminology.hl7.org/CodeSystem/v2-0203"
                }
              ]
            },
            "value": "1601716017"
          },
          {
            "assigner": {
              "identifier": {
                "system": "https://fhir.nhs.uk/Id/ods-organization-code",
                "value": "699X0"
              }
            },
            "system": "http://www.acme.org/servicerequest",
            "type": {
              "coding": [
                {
                  "code": "FILL",
                  "system": "http://terminology.hl7.org/CodeSystem/v2-0203"
                }
              ]
            },
            "value": "1001166717"
          }
        ],
        "performer": [
          {
            "identifier": {
              "system": "https://fhir.nhs.uk/Id/ods-organization-code",
              "value": "699X0"
            },
            "type": "Organization"
          }
        ],
        "status": "final",
        "subject": {
          "identifier": {
            "system": "https://fhir.nhs.uk/Id/nhs-number",
            "type": {
              "coding": [
                {
                  "code": "NH",
                  "system": "http://terminology.hl7.org/CodeSystem/v2-0203"
                }
              ]
            },
            "value": "9737383192"
          },
          "reference": "urn:uuid:4ca1afff-154e-4f42-91c0-a9b3b05b3212"
        },
        "valueDateTime": "2025-05-12T10:37:26+00:00"
      }
    },
    {
      "fullUrl": "urn:uuid:ea4954ac-8c8d-4efc-bbba-735fc1b38c24",
      "resource": {
        "resourceType": "Condition",
        "code": {
          "coding": [
            {
              "code": "363349007",
              "display": "Malignant tumour of stomach",
              "system": "http://snomed.info/sct"
            }
          ]
        },
        "onsetDateTime": "2025-01-29T10:37:26+00:00",
        "subject": {
          "identifier": {
            "system": "https://fhir.nhs.uk/Id/nhs-number",
            "type": {
              "coding": [
                {
                  "code": "NH",
                  "system": "http://terminology.hl7.org/CodeSystem/v2-0203"
                }
              ]
            },
            "value": "9737383192"
          },
          "reference": "urn:uuid:4ca1afff-154e-4f42-91c0-a9b3b05b3212"
        }
      }
    },
    {
      "fullUrl": "urn:uuid:91817c84-3ff7-4c59-9cf8-15f7744df113",
      "resource": {
        "resourceType": "Specimen",
        "accessionIdentifier": {
          "assigner": {
            "identifier": {
              "system": "https://fhir.nhs.uk/Id/ods-organization-code",
              "value": "699X0"
            }
          },
          "type": {
            "coding": [
              {
                "code": "ACSN",
                "system": "http://terminology.hl7.org/CodeSystem/v2-0203"
              }
            ]
          },
          "value": "1001166717"
        },
        "collection": {
          "collectedDateTime": "2025-01-29T10:37:26+00:00"
        },
        "identifier": [
          {
            "assigner": {
              "identifier": {
                "system": "https://fhir.nhs.uk/Id/ods-organization-code",
                "value": "R0A"
              }
            },
            "system": "urn:oid:1.2.840.114350.1.13.861.1.7.2.798268",
            "type": {
              "coding": [
                {
                  "code": "PLAC",
                  "system": "http://terminology.hl7.org/CodeSystem/v2-0203"
                }
              ]
            },
            "value": "25GEN-029GN00001"
          }
        ],
        "status": "available",
        "subject": {
          "identifier": {
            "system": "https://fhir.nhs.uk/Id/nhs-number",
            "type": {
              "coding": [
                {
                  "code": "NH",
                  "system": "http://terminology.hl7.org/CodeSystem/v2-0203"
                }
              ]
            },
            "value": "9737383192"
          },
          "reference": "urn:uuid:4ca1afff-154e-4f42-91c0-a9b3b05b3212"
        },
        "type": {
          "coding": [
            {
              "code": "258580003",
              "display": "Whole blood specimen",
              "system": "http://snomed.info/sct"
            }
          ]
        }
      }
    },
    {
      "fullUrl": "urn:uuid:181c9487-dec5-4a45-91eb-bcf16cf55b0f",
      "resource": {
        "resourceType": "ServiceRequest",
        "authoredOn": "2025-01-29T00:00:00+00:00",
        "category": [
          {
            "coding": [
              {
                "code": "116148004",
                "system": "http://snomed.info/sct"
              }
            ]
          }
        ],
        "code": {
          "coding": [
            {
              "code": "R125.1",
              "display": "Gaucher disease",
              "system": "https://fhir.nhs.uk/CodeSystem/England-GenomicTestDirectory"
            }
          ]
        },
        "encounter": {
          "identifier": {
            "assigner": {
              "identifier": {
                "system": "https://fhir.nhs.uk/Id/ods-organization-code",
                "value": "R0A"
              }
            },
            "type": {
              "coding": [
                {
                  "code": "VN",
                  "system": "http://terminology.hl7.org/CodeSystem/v2-0203"
                }
              ]
            },
            "value": "1001166717"
          },
          "reference": "urn:uuid:4d07344b-8f8a-4a01-8b95-867607d6e5d1"
        },
        "identifier": [
          {
            "assigner": {
              "identifier": {
                "system": "https://fhir.nhs.uk/Id/ods-organization-code",
                "value": "ROA"
              }
            },
            "system": "urn:oid:1.2.840.114350.1.13.861.1.7.2.798268",
            "type": {
              "coding": [
                {
                  "code": "PLAC",
                  "system": "http://terminology.hl7.org/CodeSystem/v2-0203"
                }
              ]
            },
            "value": "1601716017"
          },
          {
            "assigner": {
              "identifier": {
                "system": "https://fhir.nhs.uk/Id/ods-organization-code",
                "value": "699X0"
              }
            },
            "system": "http://www.acme.org/servicerequest",
            "type": {
              "coding": [
                {
                  "code": "FILL",
                  "system": "http://terminology.hl7.org/CodeSystem/v2-0203"
                }
              ]
            },
            "value": "1001166717"
          }
        ],
        "intent": "order",
        "note": [
          {
            "text": "Referral lab PLEASE do following tests:\\n\\nTest(s) required: WGS\\nSample type: Blood\\nTransport used: Merlin Courier\\nTracking Number: ABC123\\nSample sent to: LWH Genetics\\nBy: PDAY on: 02/04/25\\n\\nSpeciality Requesting Clinician: PAEDS\\nTest Group: Neurology\\nEthnic Group: White British\\nPatient is from consanguineous union? : Unknown\\nSpecimen Collection Status: Collect & send with order\\nInfection Risk: No Specific Risk\\nClinical details:\\n\\nTESTING\\nContact/Bleep No: 123\\n"
          }
        ],
        "reasonCode": [
          {
            "coding": [
              {
                "code": "363349007",
                "display": "Malignant tumour of stomach",
                "system": "http://snomed.info/sct"
              }
            ]
          },
          {
            "coding": [
              {
                "code": "363349007",
                "display": "Malignant tumour of stomach",
                "system": "http://snomed.info/sct"
              }
            ]
          }
        ],
        "reasonReference": [
          {
            "reference": "urn:uuid:ea4954ac-8c8d-4efc-bbba-735fc1b38c24",
            "type": "Condition"
          }
        ],
        "requester": {
          "reference": "urn:uuid:fa4c9345-6d89-4916-8fd3-a04c27f8dc1d"
        },
        "specimen": [
          {
            "reference": "urn:uuid:91817c84-3ff7-4c59-9cf8-15f7744df113",
            "type": "Specimen"
          }
        ],
        "status": "active",
        "subject": {
          "identifier": {
            "system": "https://fhir.nhs.uk/Id/nhs-number",
            "type": {
              "coding": [
                {
                  "code": "NH",
                  "system": "http://terminology.hl7.org/CodeSystem/v2-0203"
                }
              ]
            },
            "value": "9737383192"
          },
          "reference": "urn:uuid:4ca1afff-154e-4f42-91c0-a9b3b05b3212"
        },
        "supportingInfo": [
          {
            "reference": "urn:uuid:5a552148-10d7-4b4c-9ffc-89951cf9a25e",
            "type": "Observation"
          },
          {
            "reference": "urn:uuid:196a7c86-dbbd-4e10-8fec-a63172aae3d4",
            "type": "Observation"
          },
          {
            "reference": "urn:uuid:731542e9-f46f-4c55-afeb-77587f217842",
            "type": "Observation"
          },
          {
            "reference": "urn:uuid:b90062d3-acba-4286-a2f1-83cb9e9014ea",
            "type": "Observation"
          },
          {
            "reference": "urn:uuid:0263020b-3463-44e7-9602-95ab0bcc162b",
            "type": "Observation"
          },
          {
            "reference": "urn:uuid:9ddcbd55-5219-43f9-9b3a-925b9e00c5b4",
            "type": "Observation"
          },
          {
            "reference": "urn:uuid:8cf333e6-81bb-402d-a3c5-1a202a6a464e",
            "type": "Observation"
          },
          {
            "reference": "urn:uuid:e317f624-ef13-4749-8fc2-4e3d38216735",
            "type": "Observation"
          },
          {
            "reference": "urn:uuid:cd115645-195e-4a3b-a1a6-d4e6a55591a0",
            "type": "Observation"
          },
          {
            "reference": "urn:uuid:87b7b2cf-dde8-4950-a246-3b32e075ecd5",
            "type": "Observation"
          },
          {
            "reference": "urn:uuid:7f41954d-f5b5-4011-8287-2b93a37adee4",
            "type": "Observation"
          },
          {
            "reference": "urn:uuid:76eb3f66-8eb7-4ccf-ba09-545bc582a7b3",
            "type": "Observation"
          },
          {
            "reference": "urn:uuid:d407e153-de34-4ab7-bd5a-2784e298da76",
            "type": "Observation"
          },
          {
            "reference": "urn:uuid:3e6143ea-f443-463f-a789-d7577ba2ff84",
            "type": "Observation"
          },
          {
            "reference": "urn:uuid:4ea646a8-86fa-4ae1-b66e-e6502b08b593",
            "type": "Observation"
          }
        ]
      }
    }
  ],
  "identifier": {
    "value": "urn:uuid:9612365d-52a4-4fab-87e7-8a09d753f095"
  },
  "timestamp": "2024-10-13T10:33:00+00:00",
  "type": "message"
}