{
  "resourceType": "Bundle",
  "entry": [
    {
      "fullUrl": "urn:uuid:a054a8c2-92f6-4982-9d96-43b89b725327",
      "resource": {
        "resourceType": "MessageHeader",
        "destination": [
          {
            "endpoint": "https//fhir.mft.nhs.uk/Endpoint/LIMS",
            "receiver": {
              "identifier": {
                "system": "https://fhir.nhs.uk/Id/ods-organization-code",
                "value": "699X0"
              }
            }
          }
        ],
        "eventCoding": {
          "code": "O21",
          "system": "http://terminology.hl7.org/CodeSystem/v2-0003"
        },
        "focus": [
          {
            "reference": "urn:uuid:ea6fb558-7be1-43be-a5b9-5556cd843316"
          }
        ],
        "sender": {
          "identifier": {
            "system": "https://fhir.nhs.uk/Id/ods-organization-code",
            "value": "R0A"
          }
        },
        "source": {
          "endpoint": "https://fhir.nwgenomics.nhs.uk/Endpoint/HIVE",
          "software": "NW GLH"
        }
      }
    },
    {
      "fullUrl": "urn:uuid:c573dadb-faa8-430e-9222-1ae2c8d4063d",
      "resource": {
        "resourceType": "Patient",
        "address": [
          {
            "postalCode": "M13 9PL"
          }
        ],
        "birthDate": "1972-09-21",
        "gender": "female",
        "identifier": [
          {
            "extension": [
              {
                "url": "https://fhir.hl7.org.uk/StructureDefinition/Extension-UKCore-NHSNumberVerificationStatus",
                "valueCodeableConcept": {
                  "coding": [
                    {
                      "code": "05",
                      "display": "Trace needs to be resolved - (NHS number or patient detail conflict)",
                      "system": "https://fhir.hl7.org.uk/CodeSystem/UKCore-NHSNumberVerificationStatusEngland"
                    }
                  ]
                }
              }
            ],
            "system": "https://fhir.nhs.uk/Id/nhs-number",
            "type": {
              "coding": [
                {
                  "code": "NH",
                  "system": "http://terminology.hl7.org/CodeSystem/v2-0203"
                }
              ]
            },
            "value": "9737383192"
          },
          {
            "assigner": {
              "identifier": {
                "system": "https://fhir.nhs.uk/Id/ods-organization-code",
                "value": "R0A"
              }
            },
            "system": "urn:oid:1.2.840.114350.1.13.611.3.7.5.737384.14",
            "type": {
              "coding": [
                {
                  "code": "MR",
                  "system": "http://terminology.hl7.org/CodeSystem/v2-0203"
                }
              ]
            },
            "value": "1234567"
          }
        ],
        "name": [
          {
            "family": "MANCHESTER",
            "given": [
              "SANSA"
            ]
          }
        ]
      }
    },
    {
      "fullUrl": "urn:uuid:63955c4d-e4f1-4412-b7ea-2c9f9b5d9591",
      "resource": {
        "resourceType": "Encounter",
        "class": {
          "code": "OBSENC",
          "system": "http://terminology.hl7.org/CodeSystem/v3-ActCode"
        },
        "identifier": [
          {
            "assigner": {
              "identifier": {
                "system": "https://fhir.nhs.uk/Id/ods-organization-code",
                "value": "R0A"
              }
            },
            "type": {
              "coding": [
                {
                  "code": "VN",
                  "system": "http://terminology.hl7.org/CodeSystem/v2-0203"
                }
              ]
            },
            "value": "1001166717"
          }
        ],
        "location": [
          {
            "location": {
              "identifier": {
                "value": "^^^R0A09^^^^^^^R0A"
              }
            }
          }
        ],
        "serviceType": {
          "coding": [
            {
              "code": "100"
            }
          ]
        },
        "status": "finished",
        "subject": {
          "identifier": {
            "system": "https://fhir.nhs.uk/Id/nhs-number",
            "type": {
              "coding": [
                {
                  "code": "NH",
                  "system": "http://terminology.hl7.org/CodeSystem/v2-0203"
                }
              ]
            },
            "value": "9737383192"
          },
          "reference": "urn:uuid:c573dadb-faa8-430e-9222-1ae2c8d4063d"
        }
      }
    },
    {
      "fullUrl": "urn:uuid:9c0eccce-c76d-4601-b16a-bd1214fcaad2",
      "resource": {
        "resourceType": "Practitioner",
        "identifier": [
          {
            "system": "https://fhir.hl7.org.uk/Id/gmc-number",
            "type": {
              "coding": [
                {
                  "code": "LN",
                  "system": "http://terminology.hl7.org/CodeSystem/v2-0203"
                }
              ]
            },
            "value": "C3456789"
          },
          {
            "value": "C3456789"
          }
        ],
        "name": [
          {
            "family": "Darwin",
            "given": [
              "Samuel"
            ],
            "prefix": [
              "Dr"
            ]
          }
        ]
      }
    },
    {
      "fullUrl": "urn:uuid:ae4ad5d3-a91f-4af1-95b3-eeda9cda1325",
      "resource": {
        "resourceType": "PractitionerRole",
        "organization": {
          "display": "Manchester University NHS Foundation Trust",
          "identifier": {
            "system": "https://fhir.nhs.uk/Id/ods-organization-code",
            "value": "R0A"
          }
        },
        "practitioner": {
          "display": "Darwin, Samuel",
          "identifier": {
            "system": "https://fhir.hl7.org.uk/Id/gmc-number",
            "type": {
              "coding": [
                {
                  "code": "LN",
                  "system": "http://terminology.hl7.org/CodeSystem/v2-0203"
                }
              ]
            },
            "value": "C3456789"
          },
          "reference": "urn:uuid:9c0eccce-c76d-4601-b16a-bd1214fcaad2"
        }
      }
    },
    {
      "fullUrl": "urn:uuid:762c5dec-1ce0-4499-9362-8ceb8ec3701f",
      "resource": {
        "resourceType": "Observation",
        "category": [
          {
            "coding": [
              {
                "code": "laboratory",
                "system": "http://terminology.hl7.org/CodeSystem/observation-category"
              }
            ]
          },
          {
            "coding": [
              {
                "code": "GE",
                "system": "http://terminology.hl7.org/CodeSystem/v2-0074"
              }
            ]
          }
        ],
        "code": {
          "coding": [
            {
              "code": "GENEAP",
              "display": "GENETICS TEST PERFORMABLE",
              "system": "https://fhir.nwgenomics.nhs.uk/CodeSystem/NWGMSA"
            }
          ]
        },
        "effectiveDateTime": "2025-01-29T10:37:26+00:00",
        "identifier": [
          {
            "assigner": {
              "identifier": {
                "system": "https://fhir.nhs.uk/Id/ods-organization-code",
                "value": "ROA"
              }
            },
            "system": "urn:oid:1.2.840.114350.1.13.861.1.7.2.798268",
            "type": {
              "coding": [
                {
                  "code": "PLAC",
                  "system": "http://terminology.hl7.org/CodeSystem/v2-0203"
                }
              ]
            },
            "value": "1601716017"
          },
          {
            "assigner": {
              "identifier": {
                "system": "https://fhir.nhs.uk/Id/ods-organization-code",
                "value": "699X0"
              }
            },
            "system": "http://www.acme.org/servicerequest",
            "type": {
              "coding": [
                {
                  "code": "FILL",
                  "system": "http://terminology.hl7.org/CodeSystem/v2-0203"
                }
              ]
            },
            "value": "1001166717"
          }
        ],
        "performer": [
          {
            "identifier": {
              "system": "https://fhir.nhs.uk/Id/ods-organization-code",
              "value": "699X0"
            },
            "type": "Organization"
          }
        ],
        "status": "final",
        "subject": {
          "identifier": {
            "system": "https://fhir.nhs.uk/Id/nhs-number",
            "type": {
              "coding": [
                {
                  "code": "NH",
                  "system": "http://terminology.hl7.org/CodeSystem/v2-0203"
                }
              ]
            },
            "value": "9737383192"
          },
          "reference": "urn:uuid:c573dadb-faa8-430e-9222-1ae2c8d4063d"
        }
      }
    },
    {
      "fullUrl": "urn:uuid:4597d8ba-fdba-43af-ba87-43db35483988",
      "resource": {
        "resourceType": "Observation",
        "category": [
          {
            "coding": [
              {
                "code": "laboratory",
                "system": "http://terminology.hl7.org/CodeSystem/observation-category"
              }
            ]
          },
          {
            "coding": [
              {
                "code": "GE",
                "system": "http://terminology.hl7.org/CodeSystem/v2-0074"
              }
            ]
          }
        ],
        "code": {
          "coding": [
            {
              "code": "230056",
              "display": "What Type of Referral Do You Require?",
              "system": "https://fhir.nwgenomics.nhs.uk/CodeSystem/NWGMSA"
            }
          ]
        },
        "effectiveDateTime": "2025-01-29T10:37:26+00:00",
        "identifier": [
          {
            "assigner": {
              "identifier": {
                "system": "https://fhir.nhs.uk/Id/ods-organization-code",
                "value": "ROA"
              }
            },
            "system": "urn:oid:1.2.840.114350.1.13.861.1.7.2.798268",
            "type": {
              "coding": [
                {
                  "code": "PLAC",
                  "system": "http://terminology.hl7.org/CodeSystem/v2-0203"
                }
              ]
            },
            "value": "1601716017"
          },
          {
            "assigner": {
              "identifier": {
                "system": "https://fhir.nhs.uk/Id/ods-organization-code",
                "value": "699X0"
              }
            },
            "system": "http://www.acme.org/servicerequest",
            "type": {
              "coding": [
                {
                  "code": "FILL",
                  "system": "http://terminology.hl7.org/CodeSystem/v2-0203"
                }
              ]
            },
            "value": "1001166717"
          }
        ],
        "performer": [
          {
            "identifier": {
              "system": "https://fhir.nhs.uk/Id/ods-organization-code",
              "value": "699X0"
            },
            "type": "Organization"
          }
        ],
        "status": "final",
        "subject": {
          "identifier": {
            "system": "https://fhir.nhs.uk/Id/nhs-number",
            "type": {
              "coding": [
                {
                  "code": "NH",
                  "system": "http://terminology.hl7.org/CodeSystem/v2-0203"
                }
              ]
            },
            "value": "9737383192"
          },
          "reference": "urn:uuid:c573dadb-faa8-430e-9222-1ae2c8d4063d"
        },
        "valueCodeableConcept": {
          "coding": [
            {
              "code": "1186936003",
              "display": "Storage of specimen (procedure)",
              "system": "http://snomed.info/sct"
            }
          ]
        }
      }
    },
    {
      "fullUrl": "urn:uuid:4c750378-f78f-4006-87ea-7586bda32bdf",
      "resource": {
        "resourceType": "Observation",
        "category": [
          {
            "coding": [
              {
                "code": "laboratory",
                "system": "http://terminology.hl7.org/CodeSystem/observation-category"
              }
            ]
          },
          {
            "coding": [
              {
                "code": "GE",
                "system": "http://terminology.hl7.org/CodeSystem/v2-0074"
              }
            ]
          }
        ],
        "code": {
          "coding": [
            {
              "code": "281269004",
              "display": "High infection risk sample",
              "system": "http://snomed.info/sct"
            }
          ]
        },
        "effectiveDateTime": "2025-01-29T10:37:26+00:00",
        "identifier": [
          {
            "assigner": {
              "identifier": {
                "system": "https://fhir.nhs.uk/Id/ods-organization-code",
                "value": "ROA"
              }
            },
            "system": "urn:oid:1.2.840.114350.1.13.861.1.7.2.798268",
            "type": {
              "coding": [
                {
                  "code": "PLAC",
                  "system": "http://terminology.hl7.org/CodeSystem/v2-0203"
                }
              ]
            },
            "value": "1601716017"
          },
          {
            "assigner": {
              "identifier": {
                "system": "https://fhir.nhs.uk/Id/ods-organization-code",
                "value": "699X0"
              }
            },
            "system": "http://www.acme.org/servicerequest",
            "type": {
              "coding": [
                {
                  "code": "FILL",
                  "system": "http://terminology.hl7.org/CodeSystem/v2-0203"
                }
              ]
            },
            "value": "1001166717"
          }
        ],
        "performer": [
          {
            "identifier": {
              "system": "https://fhir.nhs.uk/Id/ods-organization-code",
              "value": "699X0"
            },
            "type": "Organization"
          }
        ],
        "status": "final",
        "subject": {
          "identifier": {
            "system": "https://fhir.nhs.uk/Id/nhs-number",
            "type": {
              "coding": [
                {
                  "code": "NH",
                  "system": "http://terminology.hl7.org/CodeSystem/v2-0203"
                }
              ]
            },
            "value": "9737383192"
          },
          "reference": "urn:uuid:c573dadb-faa8-430e-9222-1ae2c8d4063d"
        },
        "valueCodeableConcept": {
          "coding": [
            {
              "code": "LA32-8",
              "display": "No",
              "system": "http://loinc.org"
            }
          ]
        }
      }
    },
    {
      "fullUrl": "urn:uuid:bf35b586-e91a-41e5-8f23-ffcfe1be6425",
      "resource": {
        "resourceType": "Observation",
        "category": [
          {
            "coding": [
              {
                "code": "laboratory",
                "system": "http://terminology.hl7.org/CodeSystem/observation-category"
              }
            ]
          },
          {
            "coding": [
              {
                "code": "GE",
                "system": "http://terminology.hl7.org/CodeSystem/v2-0074"
              }
            ]
          }
        ],
        "code": {
          "coding": [
            {
              "code": "230016",
              "display": "Test Type",
              "system": "https://fhir.nwgenomics.nhs.uk/CodeSystem/NWGMSA"
            }
          ]
        },
        "effectiveDateTime": "2025-01-29T10:37:26+00:00",
        "identifier": [
          {
            "assigner": {
              "identifier": {
                "system": "https://fhir.nhs.uk/Id/ods-organization-code",
                "value": "ROA"
              }
            },
            "system": "urn:oid:1.2.840.114350.1.13.861.1.7.2.798268",
            "type": {
              "coding": [
                {
                  "code": "PLAC",
                  "system": "http://terminology.hl7.org/CodeSystem/v2-0203"
                }
              ]
            },
            "value": "1601716017"
          },
          {
            "assigner": {
              "identifier": {
                "system": "https://fhir.nhs.uk/Id/ods-organization-code",
                "value": "699X0"
              }
            },
            "system": "http://www.acme.org/servicerequest",
            "type": {
              "coding": [
                {
                  "code": "FILL",
                  "system": "http://terminology.hl7.org/CodeSystem/v2-0203"
                }
              ]
            },
            "value": "1001166717"
          }
        ],
        "performer": [
          {
            "identifier": {
              "system": "https://fhir.nhs.uk/Id/ods-organization-code",
              "value": "699X0"
            },
            "type": "Organization"
          }
        ],
        "status": "final",
        "subject": {
          "identifier": {
            "system": "https://fhir.nhs.uk/Id/nhs-number",
            "type": {
              "coding": [
                {
                  "code": "NH",
                  "system": "http://terminology.hl7.org/CodeSystem/v2-0203"
                }
              ]
            },
            "value": "9737383192"
          },
          "reference": "urn:uuid:c573dadb-faa8-430e-9222-1ae2c8d4063d"
        },
        "valueString": "Diagnostic Screen/Test"
      }
    },
    {
      "fullUrl": "urn:uuid:88f8af1e-dcd8-49a3-aae0-3dfc36780071",
      "resource": {
        "resourceType": "Observation",
        "category": [
          {
            "coding": [
              {
                "code": "laboratory",
                "system": "http://terminology.hl7.org/CodeSystem/observation-category"
              }
            ]
          },
          {
            "coding": [
              {
                "code": "GE",
                "system": "http://terminology.hl7.org/CodeSystem/v2-0074"
              }
            ]
          }
        ],
        "code": {
          "coding": [
            {
              "code": "77386006",
              "display": "Pregnancy",
              "system": "http://snomed.info/sct"
            }
          ]
        },
        "effectiveDateTime": "2025-01-29T10:37:26+00:00",
        "identifier": [
          {
            "assigner": {
              "identifier": {
                "system": "https://fhir.nhs.uk/Id/ods-organization-code",
                "value": "ROA"
              }
            },
            "system": "urn:oid:1.2.840.114350.1.13.861.1.7.2.798268",
            "type": {
              "coding": [
                {
                  "code": "PLAC",
                  "system": "http://terminology.hl7.org/CodeSystem/v2-0203"
                }
              ]
            },
            "value": "1601716017"
          },
          {
            "assigner": {
              "identifier": {
                "system": "https://fhir.nhs.uk/Id/ods-organization-code",
                "value": "699X0"
              }
            },
            "system": "http://www.acme.org/servicerequest",
            "type": {
              "coding": [
                {
                  "code": "FILL",
                  "system": "http://terminology.hl7.org/CodeSystem/v2-0203"
                }
              ]
            },
            "value": "1001166717"
          }
        ],
        "performer": [
          {
            "identifier": {
              "system": "https://fhir.nhs.uk/Id/ods-organization-code",
              "value": "699X0"
            },
            "type": "Organization"
          }
        ],
        "status": "final",
        "subject": {
          "identifier": {
            "system": "https://fhir.nhs.uk/Id/nhs-number",
            "type": {
              "coding": [
                {
                  "code": "NH",
                  "system": "http://terminology.hl7.org/CodeSystem/v2-0203"
                }
              ]
            },
            "value": "9737383192"
          },
          "reference": "urn:uuid:c573dadb-faa8-430e-9222-1ae2c8d4063d"
        },
        "valueCodeableConcept": {
          "coding": [
            {
              "code": "LA33-6",
              "display": "Yes",
              "system": "http://loinc.org"
            }
          ]
        }
      }
    },
    {
      "fullUrl": "urn:uuid:be04eedb-587c-4b15-a4ba-9068c1382728",
      "resource": {
        "resourceType": "Observation",
        "category": [
          {
            "coding": [
              {
                "code": "laboratory",
                "system": "http://terminology.hl7.org/CodeSystem/observation-category"
              }
            ]
          },
          {
            "coding": [
              {
                "code": "GE",
                "system": "http://terminology.hl7.org/CodeSystem/v2-0074"
              }
            ]
          }
        ],
        "code": {
          "coding": [
            {
              "code": "231284",
              "display": "Please Select R240 Test(s):",
              "system": "https://fhir.nwgenomics.nhs.uk/CodeSystem/NWGMSA"
            }
          ]
        },
        "effectiveDateTime": "2025-01-29T10:37:26+00:00",
        "identifier": [
          {
            "assigner": {
              "identifier": {
                "system": "https://fhir.nhs.uk/Id/ods-organization-code",
                "value": "ROA"
              }
            },
            "system": "urn:oid:1.2.840.114350.1.13.861.1.7.2.798268",
            "type": {
              "coding": [
                {
                  "code": "PLAC",
                  "system": "http://terminology.hl7.org/CodeSystem/v2-0203"
                }
              ]
            },
            "value": "1601716017"
          },
          {
            "assigner": {
              "identifier": {
                "system": "https://fhir.nhs.uk/Id/ods-organization-code",
                "value": "699X0"
              }
            },
            "system": "http://www.acme.org/servicerequest",
            "type": {
              "coding": [
                {
                  "code": "FILL",
                  "system": "http://terminology.hl7.org/CodeSystem/v2-0203"
                }
              ]
            },
            "value": "1001166717"
          }
        ],
        "performer": [
          {
            "identifier": {
              "system": "https://fhir.nhs.uk/Id/ods-organization-code",
              "value": "699X0"
            },
            "type": "Organization"
          }
        ],
        "status": "final",
        "subject": {
          "identifier": {
            "system": "https://fhir.nhs.uk/Id/nhs-number",
            "type": {
              "coding": [
                {
                  "code": "NH",
                  "system": "http://terminology.hl7.org/CodeSystem/v2-0203"
                }
              ]
            },
            "value": "9737383192"
          },
          "reference": "urn:uuid:c573dadb-faa8-430e-9222-1ae2c8d4063d"
        },
        "valueString": "R240.1: Targeted variant testing"
      }
    },
    {
      "fullUrl": "urn:uuid:086852c0-d9e4-4793-a205-e50005f5cf1a",
      "resource": {
        "resourceType": "Observation",
        "category": [
          {
            "coding": [
              {
                "code": "laboratory",
                "system": "http://terminology.hl7.org/CodeSystem/observation-category"
              }
            ]
          },
          {
            "coding": [
              {
                "code": "GE",
                "system": "http://terminology.hl7.org/CodeSystem/v2-0074"
              }
            ]
          }
        ],
        "code": {
          "coding": [
            {
              "code": "231285",
              "display": "Please Select R242 Test(s):",
              "system": "https://fhir.nwgenomics.nhs.uk/CodeSystem/NWGMSA"
            }
          ]
        },
        "effectiveDateTime": "2025-01-29T10:37:26+00:00",
        "identifier": [
          {
            "assigner": {
              "identifier": {
                "system": "https://fhir.nhs.uk/Id/ods-organization-code",
                "value": "ROA"
              }
            },
            "system": "urn:oid:1.2.840.114350.1.13.861.1.7.2.798268",
            "type": {
              "coding": [
                {
                  "code": "PLAC",
                  "system": "http://terminology.hl7.org/CodeSystem/v2-0203"
                }
              ]
            },
            "value": "1601716017"
          },
          {
            "assigner": {
              "identifier": {
                "system": "https://fhir.nhs.uk/Id/ods-organization-code",
                "value": "699X0"
              }
            },
            "system": "http://www.acme.org/servicerequest",
            "type": {
              "coding": [
                {
                  "code": "FILL",
                  "system": "http://terminology.hl7.org/CodeSystem/v2-0203"
                }
              ]
            },
            "value": "1001166717"
          }
        ],
        "performer": [
          {
            "identifier": {
              "system": "https://fhir.nhs.uk/Id/ods-organization-code",
              "value": "699X0"
            },
            "type": "Organization"
          }
        ],
        "status": "final",
        "subject": {
          "identifier": {
            "system": "https://fhir.nhs.uk/Id/nhs-number",
            "type": {
              "coding": [
                {
                  "code": "NH",
                  "system": "http://terminology.hl7.org/CodeSystem/v2-0203"
                }
              ]
            },
            "value": "9737383192"
          },
          "reference": "urn:uuid:c573dadb-faa8-430e-9222-1ae2c8d4063d"
        },
        "valueString": "R242.1: Targeted variant testing"
      }
    },
    {
      "fullUrl": "urn:uuid:81a4b7af-2c4b-4cce-8664-4db7410e2101",
      "resource": {
        "resourceType": "Observation",
        "category": [
          {
            "coding": [
              {
                "code": "laboratory",
                "system": "http://terminology.hl7.org/CodeSystem/observation-category"
              }
            ]
          },
          {
            "coding": [
              {
                "code": "GE",
                "system": "http://terminology.hl7.org/CodeSystem/v2-0074"
              }
            ]
          }
        ],
        "code": {
          "coding": [
            {
              "code": "230027",
              "display": "Email Addresses of Non-MFT Clinicians for Result Reports",
              "system": "https://fhir.nwgenomics.nhs.uk/CodeSystem/NWGMSA"
            }
          ]
        },
        "effectiveDateTime": "2025-01-29T10:37:26+00:00",
        "identifier": [
          {
            "assigner": {
              "identifier": {
                "system": "https://fhir.nhs.uk/Id/ods-organization-code",
                "value": "ROA"
              }
            },
            "system": "urn:oid:1.2.840.114350.1.13.861.1.7.2.798268",
            "type": {
              "coding": [
                {
                  "code": "PLAC",
                  "system": "http://terminology.hl7.org/CodeSystem/v2-0203"
                }
              ]
            },
            "value": "1601716017"
          },
          {
            "assigner": {
              "identifier": {
                "system": "https://fhir.nhs.uk/Id/ods-organization-code",
                "value": "699X0"
              }
            },
            "system": "http://www.acme.org/servicerequest",
            "type": {
              "coding": [
                {
                  "code": "FILL",
                  "system": "http://terminology.hl7.org/CodeSystem/v2-0203"
                }
              ]
            },
            "value": "1001166717"
          }
        ],
        "performer": [
          {
            "identifier": {
              "system": "https://fhir.nhs.uk/Id/ods-organization-code",
              "value": "699X0"
            },
            "type": "Organization"
          }
        ],
        "status": "final",
        "subject": {
          "identifier": {
            "system": "https://fhir.nhs.uk/Id/nhs-number",
            "type": {
              "coding": [
                {
                  "code": "NH",
                  "system": "http://terminology.hl7.org/CodeSystem/v2-0203"
                }
              ]
            },
            "value": "9737383192"
          },
          "reference": "urn:uuid:c573dadb-faa8-430e-9222-1ae2c8d4063d"
        },
        "valueString": "charu"
      }
    },
    {
      "fullUrl": "urn:uuid:64e2aa3b-26bf-4c17-bdab-337afe91b6b6",
      "resource": {
        "resourceType": "Observation",
        "category": [
          {
            "coding": [
              {
                "code": "laboratory",
                "system": "http://terminology.hl7.org/CodeSystem/observation-category"
              }
            ]
          },
          {
            "coding": [
              {
                "code": "GE",
                "system": "http://terminology.hl7.org/CodeSystem/v2-0074"
              }
            ]
          }
        ],
        "code": {
          "coding": [
            {
              "code": "762911000000102",
              "display": "Informed consent given for treatment",
              "system": "http://snomed.info/sct"
            }
          ]
        },
        "effectiveDateTime": "2025-01-29T10:37:26+00:00",
        "identifier": [
          {
            "assigner": {
              "identifier": {
                "system": "https://fhir.nhs.uk/Id/ods-organization-code",
                "value": "ROA"
              }
            },
            "system": "urn:oid:1.2.840.114350.1.13.861.1.7.2.798268",
            "type": {
              "coding": [
                {
                  "code": "PLAC",
                  "system": "http://terminology.hl7.org/CodeSystem/v2-0203"
                }
              ]
            },
            "value": "1601716017"
          },
          {
            "assigner": {
              "identifier": {
                "system": "https://fhir.nhs.uk/Id/ods-organization-code",
                "value": "699X0"
              }
            },
            "system": "http://www.acme.org/servicerequest",
            "type": {
              "coding": [
                {
                  "code": "FILL",
                  "system": "http://terminology.hl7.org/CodeSystem/v2-0203"
                }
              ]
            },
            "value": "1001166717"
          }
        ],
        "performer": [
          {
            "identifier": {
              "system": "https://fhir.nhs.uk/Id/ods-organization-code",
              "value": "699X0"
            },
            "type": "Organization"
          }
        ],
        "status": "final",
        "subject": {
          "identifier": {
            "system": "https://fhir.nhs.uk/Id/nhs-number",
            "type": {
              "coding": [
                {
                  "code": "NH",
                  "system": "http://terminology.hl7.org/CodeSystem/v2-0203"
                }
              ]
            },
            "value": "9737383192"
          },
          "reference": "urn:uuid:c573dadb-faa8-430e-9222-1ae2c8d4063d"
        },
        "valueCodeableConcept": {
          "coding": [
            {
              "code": "LA33-6",
              "display": "Yes",
              "system": "http://loinc.org"
            }
          ]
        }
      }
    },
    {
      "fullUrl": "urn:uuid:a4096876-30d2-466d-a0ab-793ded65dc9c",
      "resource": {
        "resourceType": "Observation",
        "category": [
          {
            "coding": [
              {
                "code": "laboratory",
                "system": "http://terminology.hl7.org/CodeSystem/observation-category"
              }
            ]
          },
          {
            "coding": [
              {
                "code": "GE",
                "system": "http://terminology.hl7.org/CodeSystem/v2-0074"
              }
            ]
          }
        ],
        "code": {
          "coding": [
            {
              "code": "230037",
              "display": "Please Acknowledge That a DNA Sample Will be Stored in the Laboratory on Completion of Testing",
              "system": "https://fhir.nwgenomics.nhs.uk/CodeSystem/NWGMSA"
            }
          ]
        },
        "effectiveDateTime": "2025-01-29T10:37:26+00:00",
        "identifier": [
          {
            "assigner": {
              "identifier": {
                "system": "https://fhir.nhs.uk/Id/ods-organization-code",
                "value": "ROA"
              }
            },
            "system": "urn:oid:1.2.840.114350.1.13.861.1.7.2.798268",
            "type": {
              "coding": [
                {
                  "code": "PLAC",
                  "system": "http://terminology.hl7.org/CodeSystem/v2-0203"
                }
              ]
            },
            "value": "1601716017"
          },
          {
            "assigner": {
              "identifier": {
                "system": "https://fhir.nhs.uk/Id/ods-organization-code",
                "value": "699X0"
              }
            },
            "system": "http://www.acme.org/servicerequest",
            "type": {
              "coding": [
                {
                  "code": "FILL",
                  "system": "http://terminology.hl7.org/CodeSystem/v2-0203"
                }
              ]
            },
            "value": "1001166717"
          }
        ],
        "performer": [
          {
            "identifier": {
              "system": "https://fhir.nhs.uk/Id/ods-organization-code",
              "value": "699X0"
            },
            "type": "Organization"
          }
        ],
        "status": "final",
        "subject": {
          "identifier": {
            "system": "https://fhir.nhs.uk/Id/nhs-number",
            "type": {
              "coding": [
                {
                  "code": "NH",
                  "system": "http://terminology.hl7.org/CodeSystem/v2-0203"
                }
              ]
            },
            "value": "9737383192"
          },
          "reference": "urn:uuid:c573dadb-faa8-430e-9222-1ae2c8d4063d"
        },
        "valueString": "Acknowledged"
      }
    },
    {
      "fullUrl": "urn:uuid:b5d2275b-18bf-4863-bfd1-0ddf4d501c71",
      "resource": {
        "resourceType": "Observation",
        "category": [
          {
            "coding": [
              {
                "code": "laboratory",
                "system": "http://terminology.hl7.org/CodeSystem/observation-category"
              }
            ]
          },
          {
            "coding": [
              {
                "code": "GE",
                "system": "http://terminology.hl7.org/CodeSystem/v2-0074"
              }
            ]
          }
        ],
        "code": {
          "coding": [
            {
              "code": "230039",
              "display": "Is the Person Ordering the Test the Referring Clinician",
              "system": "https://fhir.nwgenomics.nhs.uk/CodeSystem/NWGMSA"
            }
          ]
        },
        "effectiveDateTime": "2025-01-29T10:37:26+00:00",
        "identifier": [
          {
            "assigner": {
              "identifier": {
                "system": "https://fhir.nhs.uk/Id/ods-organization-code",
                "value": "ROA"
              }
            },
            "system": "urn:oid:1.2.840.114350.1.13.861.1.7.2.798268",
            "type": {
              "coding": [
                {
                  "code": "PLAC",
                  "system": "http://terminology.hl7.org/CodeSystem/v2-0203"
                }
              ]
            },
            "value": "1601716017"
          },
          {
            "assigner": {
              "identifier": {
                "system": "https://fhir.nhs.uk/Id/ods-organization-code",
                "value": "699X0"
              }
            },
            "system": "http://www.acme.org/servicerequest",
            "type": {
              "coding": [
                {
                  "code": "FILL",
                  "system": "http://terminology.hl7.org/CodeSystem/v2-0203"
                }
              ]
            },
            "value": "1001166717"
          }
        ],
        "performer": [
          {
            "identifier": {
              "system": "https://fhir.nhs.uk/Id/ods-organization-code",
              "value": "699X0"
            },
            "type": "Organization"
          }
        ],
        "status": "final",
        "subject": {
          "identifier": {
            "system": "https://fhir.nhs.uk/Id/nhs-number",
            "type": {
              "coding": [
                {
                  "code": "NH",
                  "system": "http://terminology.hl7.org/CodeSystem/v2-0203"
                }
              ]
            },
            "value": "9737383192"
          },
          "reference": "urn:uuid:c573dadb-faa8-430e-9222-1ae2c8d4063d"
        },
        "valueString": "No"
      }
    },
    {
      "fullUrl": "urn:uuid:0f2a10fc-4ce6-40f4-b764-efa125f2ef44",
      "resource": {
        "resourceType": "Observation",
        "category": [
          {
            "coding": [
              {
                "code": "laboratory",
                "system": "http://terminology.hl7.org/CodeSystem/observation-category"
              }
            ]
          },
          {
            "coding": [
              {
                "code": "GE",
                "system": "http://terminology.hl7.org/CodeSystem/v2-0074"
              }
            ]
          }
        ],
        "code": {
          "coding": [
            {
              "code": "18705-4",
              "display": "Name of Supervising Clinician",
              "system": "http://loinc.org"
            }
          ]
        },
        "effectiveDateTime": "2025-01-29T10:37:26+00:00",
        "identifier": [
          {
            "assigner": {
              "identifier": {
                "system": "https://fhir.nhs.uk/Id/ods-organization-code",
                "value": "ROA"
              }
            },
            "system": "urn:oid:1.2.840.114350.1.13.861.1.7.2.798268",
            "type": {
              "coding": [
                {
                  "code": "PLAC",
                  "system": "http://terminology.hl7.org/CodeSystem/v2-0203"
                }
              ]
            },
            "value": "1601716017"
          },
          {
            "assigner": {
              "identifier": {
                "system": "https://fhir.nhs.uk/Id/ods-organization-code",
                "value": "699X0"
              }
            },
            "system": "http://www.acme.org/servicerequest",
            "type": {
              "coding": [
                {
                  "code": "FILL",
                  "system": "http://terminology.hl7.org/CodeSystem/v2-0203"
                }
              ]
            },
            "value": "1001166717"
          }
        ],
        "performer": [
          {
            "identifier": {
              "system": "https://fhir.nhs.uk/Id/ods-organization-code",
              "value": "699X0"
            },
            "type": "Organization"
          }
        ],
        "status": "final",
        "subject": {
          "identifier": {
            "system": "https://fhir.nhs.uk/Id/nhs-number",
            "type": {
              "coding": [
                {
                  "code": "NH",
                  "system": "http://terminology.hl7.org/CodeSystem/v2-0203"
                }
              ]
            },
            "value": "9737383192"
          },
          "reference": "urn:uuid:c573dadb-faa8-430e-9222-1ae2c8d4063d"
        },
        "valueString": "DESHPANDE, CHARULATA"
      }
    },
    {
      "fullUrl": "urn:uuid:c6924860-3e2e-4ae2-9cf3-999b9e1b2928",
      "resource": {
        "resourceType": "Observation",
        "category": [
          {
            "coding": [
              {
                "code": "laboratory",
                "system": "http://terminology.hl7.org/CodeSystem/observation-category"
              }
            ]
          },
          {
            "coding": [
              {
                "code": "GE",
                "system": "http://terminology.hl7.org/CodeSystem/v2-0074"
              }
            ]
          }
        ],
        "code": {
          "coding": [
            {
              "code": "97209-1",
              "display": "Shipment tracking number",
              "system": "http://loinc.org"
            }
          ]
        },
        "effectiveDateTime": "2025-01-29T10:37:26+00:00",
        "identifier": [
          {
            "assigner": {
              "identifier": {
                "system": "https://fhir.nhs.uk/Id/ods-organization-code",
                "value": "ROA"
              }
            },
            "system": "urn:oid:1.2.840.114350.1.13.861.1.7.2.798268",
            "type": {
              "coding": [
                {
                  "code": "PLAC",
                  "system": "http://terminology.hl7.org/CodeSystem/v2-0203"
                }
              ]
            },
            "value": "1601716017"
          },
          {
            "assigner": {
              "identifier": {
                "system": "https://fhir.nhs.uk/Id/ods-organization-code",
                "value": "699X0"
              }
            },
            "system": "http://www.acme.org/servicerequest",
            "type": {
              "coding": [
                {
                  "code": "FILL",
                  "system": "http://terminology.hl7.org/CodeSystem/v2-0203"
                }
              ]
            },
            "value": "1001166717"
          }
        ],
        "performer": [
          {
            "identifier": {
              "system": "https://fhir.nhs.uk/Id/ods-organization-code",
              "value": "699X0"
            },
            "type": "Organization"
          }
        ],
        "status": "final",
        "subject": {
          "identifier": {
            "system": "https://fhir.nhs.uk/Id/nhs-number",
            "type": {
              "coding": [
                {
                  "code": "NH",
                  "system": "http://terminology.hl7.org/CodeSystem/v2-0203"
                }
              ]
            },
            "value": "9737383192"
          },
          "reference": "urn:uuid:c573dadb-faa8-430e-9222-1ae2c8d4063d"
        },
        "valueString": "UK3096580215"
      }
    },
    {
      "fullUrl": "urn:uuid:4a6ad73a-b484-44ab-90f8-5ba9006f13c0",
      "resource": {
        "resourceType": "Observation",
        "category": [
          {
            "coding": [
              {
                "code": "laboratory",
                "system": "http://terminology.hl7.org/CodeSystem/observation-category"
              }
            ]
          },
          {
            "coding": [
              {
                "code": "GE",
                "system": "http://terminology.hl7.org/CodeSystem/v2-0074"
              }
            ]
          }
        ],
        "code": {
          "coding": [
            {
              "code": "842009",
              "display": "Consanguinity",
              "system": "http://snomed.info/sct"
            }
          ]
        },
        "effectiveDateTime": "2025-01-29T10:37:26+00:00",
        "identifier": [
          {
            "assigner": {
              "identifier": {
                "system": "https://fhir.nhs.uk/Id/ods-organization-code",
                "value": "ROA"
              }
            },
            "system": "urn:oid:1.2.840.114350.1.13.861.1.7.2.798268",
            "type": {
              "coding": [
                {
                  "code": "PLAC",
                  "system": "http://terminology.hl7.org/CodeSystem/v2-0203"
                }
              ]
            },
            "value": "1601716017"
          },
          {
            "assigner": {
              "identifier": {
                "system": "https://fhir.nhs.uk/Id/ods-organization-code",
                "value": "699X0"
              }
            },
            "system": "http://www.acme.org/servicerequest",
            "type": {
              "coding": [
                {
                  "code": "FILL",
                  "system": "http://terminology.hl7.org/CodeSystem/v2-0203"
                }
              ]
            },
            "value": "1001166717"
          }
        ],
        "performer": [
          {
            "identifier": {
              "system": "https://fhir.nhs.uk/Id/ods-organization-code",
              "value": "699X0"
            },
            "type": "Organization"
          }
        ],
        "status": "final",
        "subject": {
          "identifier": {
            "system": "https://fhir.nhs.uk/Id/nhs-number",
            "type": {
              "coding": [
                {
                  "code": "NH",
                  "system": "http://terminology.hl7.org/CodeSystem/v2-0203"
                }
              ]
            },
            "value": "9737383192"
          },
          "reference": "urn:uuid:c573dadb-faa8-430e-9222-1ae2c8d4063d"
        },
        "valueCodeableConcept": {
          "coding": [
            {
              "code": "LA32-8",
              "display": "No",
              "system": "http://loinc.org"
            }
          ]
        }
      }
    },
    {
      "fullUrl": "urn:uuid:435af492-a163-4060-8057-2962d16a51e0",
      "resource": {
        "resourceType": "Observation",
        "category": [
          {
            "coding": [
              {
                "code": "laboratory",
                "system": "http://terminology.hl7.org/CodeSystem/observation-category"
              }
            ]
          },
          {
            "coding": [
              {
                "code": "GE",
                "system": "http://terminology.hl7.org/CodeSystem/v2-0074"
              }
            ]
          }
        ],
        "code": {
          "coding": [
            {
              "code": "161714006",
              "display": "Estimated date of delivery",
              "system": "http://snomed.info/sct"
            }
          ]
        },
        "effectiveDateTime": "2025-01-29T10:37:26+00:00",
        "identifier": [
          {
            "assigner": {
              "identifier": {
                "system": "https://fhir.nhs.uk/Id/ods-organization-code",
                "value": "ROA"
              }
            },
            "system": "urn:oid:1.2.840.114350.1.13.861.1.7.2.798268",
            "type": {
              "coding": [
                {
                  "code": "PLAC",
                  "system": "http://terminology.hl7.org/CodeSystem/v2-0203"
                }
              ]
            },
            "value": "1601716017"
          },
          {
            "assigner": {
              "identifier": {
                "system": "https://fhir.nhs.uk/Id/ods-organization-code",
                "value": "699X0"
              }
            },
            "system": "http://www.acme.org/servicerequest",
            "type": {
              "coding": [
                {
                  "code": "FILL",
                  "system": "http://terminology.hl7.org/CodeSystem/v2-0203"
                }
              ]
            },
            "value": "1001166717"
          }
        ],
        "performer": [
          {
            "identifier": {
              "system": "https://fhir.nhs.uk/Id/ods-organization-code",
              "value": "699X0"
            },
            "type": "Organization"
          }
        ],
        "status": "final",
        "subject": {
          "identifier": {
            "system": "https://fhir.nhs.uk/Id/nhs-number",
            "type": {
              "coding": [
                {
                  "code": "NH",
                  "system": "http://terminology.hl7.org/CodeSystem/v2-0203"
                }
              ]
            },
            "value": "9737383192"
          },
          "reference": "urn:uuid:c573dadb-faa8-430e-9222-1ae2c8d4063d"
        },
        "valueDateTime": "2025-05-12T10:37:26+00:00"
      }
    },
    {
      "fullUrl": "urn:uuid:02075cec-d7ab-4373-81db-a624cfe22449",
      "resource": {
        "resourceType": "Condition",
        "code": {
          "coding": [
            {
              "code": "363349007",
              "display": "Malignant tumour of stomach",
              "system": "http://snomed.info/sct"
            }
          ]
        },
        "onsetDateTime": "2025-01-29T10:37:26+00:00",
        "subject": {
          "identifier": {
            "system": "https://fhir.nhs.uk/Id/nhs-number",
            "type": {
              "coding": [
                {
                  "code": "NH",
                  "system": "http://terminology.hl7.org/CodeSystem/v2-0203"
                }
              ]
            },
            "value": "9737383192"
          },
          "reference": "urn:uuid:c573dadb-faa8-430e-9222-1ae2c8d4063d"
        }
      }
    },
    {
      "fullUrl": "urn:uuid:4c6a1536-798d-4ce4-9a1a-5048a1f389ee",
      "resource": {
        "resourceType": "Specimen",
        "accessionIdentifier": {
          "assigner": {
            "identifier": {
              "system": "https://fhir.nhs.uk/Id/ods-organization-code",
              "value": "699X0"
            }
          },
          "type": {
            "coding": [
              {
                "code": "ACSN",
                "system": "http://terminology.hl7.org/CodeSystem/v2-0203"
              }
            ]
          },
          "value": "1001166717"
        },
        "collection": {
          "collectedDateTime": "2025-01-29T10:37:26+00:00"
        },
        "identifier": [
          {
            "assigner": {
              "identifier": {
                "system": "https://fhir.nhs.uk/Id/ods-organization-code",
                "value": "R0A"
              }
            },
            "system": "urn:oid:1.2.840.114350.1.13.861.1.7.2.798268",
            "type": {
              "coding": [
                {
                  "code": "PLAC",
                  "system": "http://terminology.hl7.org/CodeSystem/v2-0203"
                }
              ]
            },
            "value": "25GEN-029GN00001"
          }
        ],
        "status": "available",
        "subject": {
          "identifier": {
            "system": "https://fhir.nhs.uk/Id/nhs-number",
            "type": {
              "coding": [
                {
                  "code": "NH",
                  "system": "http://terminology.hl7.org/CodeSystem/v2-0203"
                }
              ]
            },
            "value": "9737383192"
          },
          "reference": "urn:uuid:c573dadb-faa8-430e-9222-1ae2c8d4063d"
        },
        "type": {
          "coding": [
            {
              "code": "258580003",
              "display": "Whole blood specimen",
              "system": "http://snomed.info/sct"
            }
          ]
        }
      }
    },
    {
      "fullUrl": "urn:uuid:ea6fb558-7be1-43be-a5b9-5556cd843316",
      "resource": {
        "resourceType": "ServiceRequest",
        "authoredOn": "2025-01-29T00:00:00+00:00",
        "category": [
          {
            "coding": [
              {
                "code": "116148004",
                "system": "http://snomed.info/sct"
              }
            ]
          }
        ],
        "code": {
          "coding": [
            {
              "code": "R125.1",
              "system": "https://fhir.nhs.uk/CodeSystem/England-GenomicTestDirectory"
            }
          ]
        },
        "encounter": {
          "identifier": {
            "assigner": {
              "identifier": {
                "system": "https://fhir.nhs.uk/Id/ods-organization-code",
                "value": "R0A"
              }
            },
            "type": {
              "coding": [
                {
                  "code": "VN",
                  "system": "http://terminology.hl7.org/CodeSystem/v2-0203"
                }
              ]
            },
            "value": "1001166717"
          },
          "reference": "urn:uuid:63955c4d-e4f1-4412-b7ea-2c9f9b5d9591"
        },
        "identifier": [
          {
            "assigner": {
              "identifier": {
                "system": "https://fhir.nhs.uk/Id/ods-organization-code",
                "value": "ROA"
              }
            },
            "system": "urn:oid:1.2.840.114350.1.13.861.1.7.2.798268",
            "type": {
              "coding": [
                {
                  "code": "PLAC",
                  "system": "http://terminology.hl7.org/CodeSystem/v2-0203"
                }
              ]
            },
            "value": "1601716017"
          },
          {
            "assigner": {
              "identifier": {
                "system": "https://fhir.nhs.uk/Id/ods-organization-code",
                "value": "699X0"
              }
            },
            "system": "http://www.acme.org/servicerequest",
            "type": {
              "coding": [
                {
                  "code": "FILL",
                  "system": "http://terminology.hl7.org/CodeSystem/v2-0203"
                }
              ]
            },
            "value": "1001166717"
          }
        ],
        "intent": "order",
        "note": [
          {
            "text": "Referral-lab-PLEASE-do-following-tests:\\n\\nTest(s)-required:-WGS\\nSample-type:-Blood\\nTransport-used:-Merlin-Courier\\nTracking-Number:-ABC123\\nSample-sent-to:-LWH-Genetics\\nBy:-PDAY-on:-02/04/25\\n\\nSpeciality-Requesting-Clinician:-PAEDS\\nTest-Group:-Neurology\\nEthnic-Group:-White-British\\nPatient-is-from-consanguineous-union?-:-Unknown\\nSpecimen-Collection-Status:-Collect-&-send-with-order\\nInfection-Risk:-No-Specific-Risk\\nClinical-details:\\n\\nTESTING\\nContact/Bleep-No:-123\\n"
          }
        ],
        "reasonCode": [
          {
            "coding": [
              {
                "code": "363349007",
                "display": "Malignant tumour of stomach",
                "system": "http://snomed.info/sct"
              }
            ]
          },
          {
            "coding": [
              {
                "code": "363349007",
                "display": "Malignant tumour of stomach",
                "system": "http://snomed.info/sct"
              }
            ]
          }
        ],
        "reasonReference": [
          {
            "reference": "urn:uuid:02075cec-d7ab-4373-81db-a624cfe22449",
            "type": "Condition"
          }
        ],
        "requester": {
          "reference": "urn:uuid:ae4ad5d3-a91f-4af1-95b3-eeda9cda1325"
        },
        "specimen": [
          {
            "reference": "urn:uuid:4c6a1536-798d-4ce4-9a1a-5048a1f389ee",
            "type": "Specimen"
          }
        ],
        "status": "active",
        "subject": {
          "identifier": {
            "system": "https://fhir.nhs.uk/Id/nhs-number",
            "type": {
              "coding": [
                {
                  "code": "NH",
                  "system": "http://terminology.hl7.org/CodeSystem/v2-0203"
                }
              ]
            },
            "value": "9737383192"
          },
          "reference": "urn:uuid:c573dadb-faa8-430e-9222-1ae2c8d4063d"
        },
        "supportingInfo": [
          {
            "reference": "urn:uuid:762c5dec-1ce0-4499-9362-8ceb8ec3701f",
            "type": "Observation"
          },
          {
            "reference": "urn:uuid:4597d8ba-fdba-43af-ba87-43db35483988",
            "type": "Observation"
          },
          {
            "reference": "urn:uuid:4c750378-f78f-4006-87ea-7586bda32bdf",
            "type": "Observation"
          },
          {
            "reference": "urn:uuid:bf35b586-e91a-41e5-8f23-ffcfe1be6425",
            "type": "Observation"
          },
          {
            "reference": "urn:uuid:88f8af1e-dcd8-49a3-aae0-3dfc36780071",
            "type": "Observation"
          },
          {
            "reference": "urn:uuid:be04eedb-587c-4b15-a4ba-9068c1382728",
            "type": "Observation"
          },
          {
            "reference": "urn:uuid:086852c0-d9e4-4793-a205-e50005f5cf1a",
            "type": "Observation"
          },
          {
            "reference": "urn:uuid:81a4b7af-2c4b-4cce-8664-4db7410e2101",
            "type": "Observation"
          },
          {
            "reference": "urn:uuid:64e2aa3b-26bf-4c17-bdab-337afe91b6b6",
            "type": "Observation"
          },
          {
            "reference": "urn:uuid:a4096876-30d2-466d-a0ab-793ded65dc9c",
            "type": "Observation"
          },
          {
            "reference": "urn:uuid:b5d2275b-18bf-4863-bfd1-0ddf4d501c71",
            "type": "Observation"
          },
          {
            "reference": "urn:uuid:0f2a10fc-4ce6-40f4-b764-efa125f2ef44",
            "type": "Observation"
          },
          {
            "reference": "urn:uuid:c6924860-3e2e-4ae2-9cf3-999b9e1b2928",
            "type": "Observation"
          },
          {
            "reference": "urn:uuid:4a6ad73a-b484-44ab-90f8-5ba9006f13c0",
            "type": "Observation"
          },
          {
            "reference": "urn:uuid:435af492-a163-4060-8057-2962d16a51e0",
            "type": "Observation"
          }
        ]
      }
    }
  ],
  "identifier": {
    "value": "urn:uuid:9612365d-52a4-4fab-87e7-8a09d753f095"
  },
  "timestamp": "2024-10-13T10:33:00+00:00",
  "type": "message"
}